{"header":{"status":"ok"},"answer":{"type":"oois","contents":[{"type":"tour","id":"23600430","title":"Rundweg Falkenklippe - Terrainkurweg","category":{"id":"21896072","ooiType":"tour","title":"Wanderung","icon":{"url":"https://res0.oastatic.com/icons/oa/hiking/raspberry_wine/hiking.square_vector.svg","color":"#b33451"},"iconMap":{"url":"https://res0.oastatic.com/icons/oa/hiking/raspberry_wine/hiking.map_vector.svg"},"iconTransparent":{"url":"https://res0.oastatic.com/icons/oa/hiking/hiking.transparent.svg"},"strokeColor":"#b33451","mapOverlays":["hiking"],"keys":["hikingTourTrail"]},"primaryImage":{"id":"24811234","meta":{"author":{"id":"23109092","name":"Andrea Hundt","profileImageId":"23140948"},"source":{"name":"Evelyn Diederich"},"system":{"createdIn":"12","lastModifiedIn":"12"},"timestamp":{"createdAt":"2017-11-01T13:59:58Z","lastModifiedAt":"2019-03-17T16:32:20Z","changedByClientAt":"2017-11-01T14:27:41Z","firstPublishedAt":"2017-11-01T14:00:00Z"},"ranking":0,"translations":["de"],"workflow":"published"}},"images":[{"type":"image","id":"24811234","relations":["isPrimary","isGallery"],"primaryImage":{"id":"24811234","meta":{"author":{"id":"23109092","name":"Andrea Hundt","profileImageId":"23140948"},"source":{"name":"Evelyn Diederich"},"system":{"createdIn":"12","lastModifiedIn":"12"},"timestamp":{"createdAt":"2017-11-01T13:59:58Z","lastModifiedAt":"2019-03-17T16:32:20Z","changedByClientAt":"2017-11-01T14:27:41Z","firstPublishedAt":"2017-11-01T14:00:00Z"},"ranking":0,"translations":["de"],"workflow":"published"}},"meta":{"author":{"id":"23109092","name":"Andrea Hundt","profileImageId":"23140948"},"source":{"name":"Evelyn Diederich"},"system":{"createdIn":"12","lastModifiedIn":"12"},"timestamp":{"createdAt":"2017-11-01T13:59:58Z","lastModifiedAt":"2019-03-17T16:32:20Z","changedByClientAt":"2017-11-01T14:27:41Z","firstPublishedAt":"2017-11-01T14:00:00Z"},"ranking":0,"workflow":"published"},"point":[10.974294722222222,51.71586305555556],"sourceImageInfo":{"width":5184,"height":3888},"isValidImage":true}],"meta":{"author":{"id":"23109092","name":"Andrea Hundt","profileImageId":"23140948"},"source":{"type":"organisation","id":"1479238","logo":{"type":"image","id":"1962302","title":"Harz: Magische Gebirgswelt"},"labels":["verified","badgeExplorersChoice"],"name":"Harz: Magische Gebirgswelt","url":"http://www.harzinfo.de/","workflow":"published"},"system":{"createdIn":"12","lastModifiedIn":"12"},"timestamp":{"createdAt":"2017-07-25T14:20:37Z","lastModifiedAt":"2023-08-28T14:52:17Z","changedByClientAt":"2017-11-09T14:21:31Z","firstPublishedAt":"2017-11-09T14:21:31Z"},"ranking":39,"translations":["de"],"workflow":"published"},"texts":{"short":"Terrainkurweg 19","long":"<p>Ab dem Startpunkt Kirche gehen Sie wie beim Terrainkurweg 18 über den Albrechtsweg, Haldenweg und Kunstgrabenweg bis nach Altenbrak. Dort biegen Sie wieder scharf links zum Köhtenhaienweg ein und folgen diesem bis zur Querung Großes Schreckental. Nach längerem Aufstieg erreichen Sie die Wildsteinwiese. Dort folgen Sie linkerhand dem Weg zu den Falkenklippen. Die herrliche Aussicht westlich in Richtung Altenbrak und östlich in Richtung Treseburg belohnt für den Aufstieg. Sie treten nun den Rückweg von den Falkenklippen an und steigen am Flößchen steil bergab nach Tresenburg. An der Haldenbrücke angelangt, gehen Sie Bode abwärts den Haldenweg entlang und erreichen über den Albrechtsweg den Ausgangspunkt.</p>\n<p><strong>Charakeristik: </strong>langer, stark fordernder Terrainkurweg, häufiger Belastungswechsel<br/><strong>Wegelänge:</strong> 8,3 km<br/><strong>Gehzeit: </strong>2 Stunden und 15 Minuten</p>","startingPoint":"Kirche in Treseburg","destination":"Kirche in Treseburg"},"point":{"x":636364.6885342615,"z":5731289.002755232,"y":267.0},"primaryRegion":{"type":"tourismarea","id":"1043712","title":"Harz"},"regions":[{"type":"commune","id":"1032041"},{"type":"country","id":"1022089"},{"type":"district","id":"1022173"},{"type":"province","id":"1029131"},{"type":"mountainarea","id":"8872348"},{"type":"protectedarea","id":"16522486"},{"type":"protectedarea","id":"9022883"},{"type":"protectedarea","id":"9024021"},{"type":"protectedarea","id":"9023351"},{"type":"tourismarea","id":"1043712"}],"coordinates":[{"title":"DD","type":"dd","value":"51.715938, 10.973981"},{"title":"GMS","type":"dms","value":"51°42'57.4\"N 10°58'26.3\"E"},{"title":"UTM","type":"utm","value":"32U 636364 5731289"},{"title":"w3w","type":"w3w","value":"///stellt.folgen.auszuhandeln"}],"communityInfo":{"ratingDetails":{"oneStar":0,"twoStar":0,"threeStar":0,"fourStar":0,"fiveStar":0},"ratingCount":0,"commentCount":0},"geoJson":{"type":"LineString","coordinates":[{"x":636364.6885342615,"z":5731289.002755232,"y":267.66383},{"x":636368.7910199647,"z":5731288.112194224,"y":267.06911},{"x":636382.9394344301,"z":5731286.380611183,"y":265.49269},{"x":636402.3136090183,"z":5731283.121228247,"y":264.5282},{"x":636406.5182855813,"z":5731281.009343385,"y":264.47811},{"x":636407.6385301341,"z":5731280.483242054,"y":264.47037},{"x":636408.6897000717,"z":5731279.955271607,"y":264.46581},{"x":636409.8880483648,"z":5731279.097433692,"y":264.46473},{"x":636412.888363011,"z":5731278.065796274,"y":264.46262},{"x":636415.7384907707,"z":5731277.475230285,"y":264.46962},{"x":636422.6879670278,"z":5731278.6648694035,"y":264.55631},{"x":636425.5322269651,"z":5731275.737194376,"y":264.65945},{"x":636438.8196346211,"z":5731259.849442327,"y":263.66096},{"x":636443.2106596953,"z":5731255.962092898,"y":263.75064},{"x":636445.922813896,"z":5731252.808285132,"y":264.08895},{"x":636448.2775538623,"z":5731250.089937824,"y":264.71558},{"x":636450.6202549667,"z":5731247.816400113,"y":265.51105},{"x":636454.3175353624,"z":5731244.021563012,"y":266.59045},{"x":636461.7960732011,"z":5731238.437275181,"y":267.86206},{"x":636469.6047799501,"z":5731235.977878807,"y":268.34767},{"x":636486.1508495939,"z":5731222.292858486,"y":269.51784},{"x":636504.2283469153,"z":5731213.3232754385,"y":267.67649},{"x":636518.188850993,"z":5731198.121646292,"y":267.9642},{"x":636524.0829742138,"z":5731177.026101596,"y":269.33665},{"x":636516.1437535728,"z":5731156.2235965235,"y":270.40636},{"x":636496.4213403556,"z":5731149.346324249,"y":272.77872},{"x":636476.572422176,"z":5731147.1396187395,"y":276.51452},{"x":636456.7383800409,"z":5731146.936499728,"y":278.22443},{"x":636437.0301494072,"z":5731152.3010436585,"y":279.38369},{"x":636435.6335676003,"z":5731152.819660087,"y":279.38663},{"x":636430.2185042583,"z":5731153.674645525,"y":279.2929},{"x":636426.962875268,"z":5731153.920380551,"y":279.13853},{"x":636424.4851471087,"z":5731153.519469886,"y":278.97675},{"x":636422.0734855909,"z":5731153.231632083,"y":278.801},{"x":636418.1331100791,"z":5731153.236273476,"y":278.61855},{"x":636417.045941573,"z":5731152.539149489,"y":278.61388},{"x":636416.7816731405,"z":5731152.086863216,"y":278.62644},{"x":636412.9585240975,"z":5731150.314144124,"y":278.6007},{"x":636404.732521728,"z":5731147.754579702,"y":278.51949},{"x":636397.6717882128,"z":5731145.560411118,"y":278.50585},{"x":636378.0753103731,"z":5731139.132152091,"y":278.92792},{"x":636362.4705423813,"z":5731125.689809976,"y":278.85688},{"x":636344.9854646805,"z":5731115.312597632,"y":279.89864},{"x":636328.9359961881,"z":5731102.97117309,"y":282.46935},{"x":636314.9493979656,"z":5731101.2575171525,"y":283.66676},{"x":636299.4309833124,"z":5731102.50713363,"y":284.85525},{"x":636293.5053723217,"z":5731101.790493804,"y":285.94081},{"x":636282.4080551765,"z":5731098.040665822,"y":289.13472},{"x":636261.3333989802,"z":5731100.253017111,"y":292.61461},{"x":636241.0215694007,"z":5731104.934307859,"y":289.47239},{"x":636232.8734163227,"z":5731107.162320434,"y":287.11305},{"x":636228.410402348,"z":5731108.599670419,"y":285.82093},{"x":636209.885596292,"z":5731116.222746904,"y":284.39453},{"x":636191.9374731525,"z":5731125.530720331,"y":287.42555},{"x":636183.4079186879,"z":5731131.643422557,"y":288.38475},{"x":636171.2923851748,"z":5731139.996213704,"y":289.67766},{"x":636155.2905614739,"z":5731154.030789298,"y":289.78462},{"x":636141.9527683991,"z":5731169.2501970995,"y":288.40631},{"x":636132.5343709942,"z":5731182.683671256,"y":285.5957},{"x":636121.9567581208,"z":5731200.648471317,"y":280.641},{"x":636112.6856481569,"z":5731218.871137477,"y":276.15104},{"x":636110.7365594638,"z":5731229.612984793,"y":273.81506},{"x":636104.411736602,"z":5731246.245974363,"y":273.60525},{"x":636100.6307313858,"z":5731265.952305752,"y":273.34241},{"x":636096.7686653493,"z":5731286.10158381,"y":273.36006},{"x":636096.9549021466,"z":5731292.004626821,"y":272.83254},{"x":636093.7926144423,"z":5731311.83895164,"y":272.33482},{"x":636094.0208712452,"z":5731313.625647412,"y":272.06221},{"x":636093.4653225001,"z":5731321.40047778,"y":271.4801},{"x":636087.7352767246,"z":5731336.491576842,"y":271.71867},{"x":636087.2697916874,"z":5731338.3708248865,"y":271.58562},{"x":636086.2697485802,"z":5731342.127456149,"y":271.30621},{"x":636084.464897753,"z":5731352.65063919,"y":270.07464},{"x":636083.2277317621,"z":5731372.870796159,"y":268.76126},{"x":636084.3210453393,"z":5731393.821574664,"y":268.86267},{"x":636084.3211864199,"z":5731414.297705978,"y":270.50268},{"x":636083.135076732,"z":5731435.186942844,"y":270.73201},{"x":636085.3064326948,"z":5731446.930316567,"y":269.54924},{"x":636089.6400755835,"z":5731465.631641267,"y":268.90989},{"x":636094.282989534,"z":5731480.557689599,"y":268.53465},{"x":636091.1057429574,"z":5731495.828996792,"y":269.53768},{"x":636088.1627024342,"z":5731499.867013548,"y":270.9943},{"x":636082.6940526916,"z":5731505.283522672,"y":274.02742},{"x":636081.0813842634,"z":5731506.130247254,"y":274.46098},{"x":636079.2074417027,"z":5731506.413501483,"y":274.83004},{"x":636075.9670775766,"z":5731506.103447918,"y":275.58065},{"x":636061.2096763873,"z":5731497.136223676,"y":280.43147},{"x":636061.6781431843,"z":5731495.145770958,"y":280.2899},{"x":636061.7321791744,"z":5731493.144130348,"y":280.32429},{"x":636059.6359809766,"z":5731491.41829271,"y":281.27981},{"x":636059.5158759495,"z":5731493.306866443,"y":281.26088},{"x":636060.1675954657,"z":5731497.33065859,"y":280.85299},{"x":636072.1201393013,"z":5731512.899151998,"y":276.97982},{"x":636081.7451391416,"z":5731517.387783906,"y":275.06987},{"x":636085.5080807571,"z":5731526.503334249,"y":273.51572},{"x":636088.2739726861,"z":5731534.145282917,"y":271.51573},{"x":636090.0038069752,"z":5731546.87829136,"y":271.39147},{"x":636089.0909465345,"z":5731567.886193052,"y":271.42128},{"x":636079.2709756718,"z":5731585.982794113,"y":274.22892},{"x":636076.1778265435,"z":5731587.902379564,"y":274.56271},{"x":636057.4567520061,"z":5731592.627269712,"y":276.19829},{"x":636055.1023514699,"z":5731592.786277807,"y":276.30717},{"x":636049.3544919462,"z":5731593.187531855,"y":276.57423},{"x":636042.8918836173,"z":5731591.900249671,"y":277.46993},{"x":636025.9364757802,"z":5731584.988171077,"y":280.29989},{"x":636024.3989152797,"z":5731585.61437293,"y":279.82693},{"x":636023.5340114707,"z":5731584.3669138355,"y":280.33785},{"x":636023.4979545559,"z":5731583.14182463,"y":280.8956},{"x":636022.527964774,"z":5731583.226928902,"y":280.74967},{"x":636018.5850265308,"z":5731588.462112223,"y":277.60818},{"x":636004.2242009542,"z":5731580.173449586,"y":278.27957},{"x":636002.2240999838,"z":5731577.448678695,"y":279.22122},{"x":635996.9626138203,"z":5731572.632804861,"y":280.13157},{"x":635988.3766566769,"z":5731565.501570374,"y":281.3799},{"x":635983.0700130068,"z":5731557.234713531,"y":284.33966},{"x":635965.4986273261,"z":5731544.964633198,"y":285.63485},{"x":635953.7861381972,"z":5731530.738276247,"y":290.47},{"x":635936.8542279443,"z":5731517.817853911,"y":294.01446},{"x":635917.7932999526,"z":5731512.073483461,"y":292.95704},{"x":635899.3388760906,"z":5731504.342443945,"y":293.24447},{"x":635879.361821026,"z":5731496.681707679,"y":292.11936},{"x":635859.0033783497,"z":5731490.346169902,"y":289.58599},{"x":635840.8881576019,"z":5731482.847061359,"y":287.95343},{"x":635834.3532956531,"z":5731481.669390615,"y":285.61565},{"x":635813.1483561979,"z":5731483.657458721,"y":274.50716},{"x":635793.9580204402,"z":5731477.576231835,"y":274.77048},{"x":635775.7404699646,"z":5731468.739210246,"y":277.85573},{"x":635755.1448140113,"z":5731466.070050913,"y":278.29005},{"x":635746.80224491,"z":5731467.848446198,"y":276.17912},{"x":635726.8320050781,"z":5731475.322998029,"y":271.09978},{"x":635706.2038369726,"z":5731478.996291065,"y":272.13828},{"x":635684.1611162017,"z":5731481.296190754,"y":272.98647},{"x":635663.8152847941,"z":5731484.75468958,"y":272.59979},{"x":635660.3858656762,"z":5731486.331625248,"y":272.81009},{"x":635640.5799595304,"z":5731482.571361004,"y":271.46589},{"x":635622.5756332777,"z":5731476.07758168,"y":273.04037},{"x":635602.4218314153,"z":5731477.538402916,"y":275.62971},{"x":635586.5744368441,"z":5731478.224888295,"y":278.85799},{"x":635582.2321477453,"z":5731480.333732884,"y":279.02197},{"x":635563.17511665,"z":5731487.277071559,"y":280.11162},{"x":635542.6521034472,"z":5731489.6184605295,"y":286.97579},{"x":635524.6252623778,"z":5731496.81221145,"y":290.33192},{"x":635513.7161403138,"z":5731506.645616442,"y":289.65662},{"x":635499.3478209858,"z":5731519.168112408,"y":289.98262},{"x":635497.5310383416,"z":5731519.898248725,"y":290.50755},{"x":635495.3781800803,"z":5731522.845005869,"y":290.03744},{"x":635487.6115179993,"z":5731541.77684834,"y":284.05718},{"x":635474.9435514472,"z":5731557.906165287,"y":283.19466},{"x":635462.414131528,"z":5731576.59873775,"y":283.07174},{"x":635453.24533671,"z":5731596.271918936,"y":281.51091},{"x":635445.8591398854,"z":5731606.200140755,"y":283.20626},{"x":635442.1386523207,"z":5731608.325809758,"y":285.7941},{"x":635436.8720690247,"z":5731613.970980093,"y":287.50443},{"x":635423.1624114001,"z":5731630.29498621,"y":291.46691},{"x":635416.0151474683,"z":5731651.91435209,"y":292.81466},{"x":635406.1048175945,"z":5731670.899987027,"y":296.6317},{"x":635401.5640145276,"z":5731690.6975931395,"y":296.39741},{"x":635400.8130585207,"z":5731710.930869619,"y":295.0377},{"x":635401.6060312649,"z":5731712.287566672,"y":294.67989},{"x":635402.6311669277,"z":5731720.438746619,"y":293.98133},{"x":635406.570872034,"z":5731741.020616119,"y":292.20574},{"x":635407.1624079652,"z":5731762.736639929,"y":291.40303},{"x":635404.0903557659,"z":5731784.465513242,"y":290.99395},{"x":635397.5496632952,"z":5731804.098106619,"y":291.37976},{"x":635398.904824071,"z":5731810.255065386,"y":290.56804},{"x":635404.5322832217,"z":5731832.328960158,"y":288.43114},{"x":635406.8653978499,"z":5731853.535367941,"y":288.32841},{"x":635407.3883973075,"z":5731857.221750913,"y":288.36615},{"x":635403.4619434723,"z":5731867.020415409,"y":289.31047},{"x":635395.9134724252,"z":5731872.71558966,"y":290.41256},{"x":635379.3528074413,"z":5731874.27376929,"y":291.26435},{"x":635376.4217834227,"z":5731872.748356427,"y":291.20392},{"x":635369.2049198564,"z":5731866.1000965545,"y":291.09749},{"x":635353.9546527362,"z":5731854.896050411,"y":291.02707},{"x":635345.95335422,"z":5731843.9980158545,"y":291.90924},{"x":635334.6240928653,"z":5731828.33675163,"y":293.39378},{"x":635321.2018379138,"z":5731813.398293945,"y":294.30199},{"x":635309.6950813909,"z":5731796.6195004685,"y":295.10731},{"x":635306.1782110223,"z":5731793.743010379,"y":294.96959},{"x":635304.2528769767,"z":5731790.7979698945,"y":295.0476},{"x":635291.2273293794,"z":5731779.09744779,"y":293.98778},{"x":635288.8065651769,"z":5731776.584244313,"y":293.72369},{"x":635288.0736863879,"z":5731775.563026749,"y":293.6693},{"x":635286.3738578326,"z":5731774.515851941,"y":293.36325},{"x":635281.2918667555,"z":5731768.14760528,"y":292.74769},{"x":635279.3614580678,"z":5731752.5162229985,"y":294.26899},{"x":635280.8187802751,"z":5731739.42399545,"y":296.81722},{"x":635280.8934056906,"z":5731736.643933725,"y":297.31639},{"x":635282.4265973028,"z":5731728.45017739,"y":299.33072},{"x":635282.5793420994,"z":5731707.310584745,"y":303.76696},{"x":635280.9690380786,"z":5731702.927338363,"y":304.17732},{"x":635279.7701592103,"z":5731698.666418908,"y":304.74069},{"x":635278.4122457986,"z":5731695.180209113,"y":305.07267},{"x":635264.6470882264,"z":5731680.1214411715,"y":303.07845},{"x":635249.1103505187,"z":5731666.68441031,"y":298.45912},{"x":635235.5010679055,"z":5731650.962217639,"y":294.04165},{"x":635220.4834521295,"z":5731636.203822369,"y":287.01694},{"x":635224.3806106225,"z":5731614.608294126,"y":301.41771},{"x":635223.6075665819,"z":5731607.354189227,"y":304.11408},{"x":635221.2211401894,"z":5731595.828061806,"y":307.57404},{"x":635218.7853307325,"z":5731593.870906933,"y":306.73266},{"x":635215.223510495,"z":5731592.662521219,"y":304.78322},{"x":635207.9846800303,"z":5731584.233412499,"y":303.94212},{"x":635201.5115668215,"z":5731575.602291381,"y":304.27609},{"x":635183.9359535283,"z":5731566.005677216,"y":301.12268},{"x":635183.0648792764,"z":5731564.980770801,"y":301.3065},{"x":635164.9753986504,"z":5731553.923771153,"y":300.33168},{"x":635159.253968392,"z":5731550.765708255,"y":299.81851},{"x":635155.2473753204,"z":5731548.0987675935,"y":299.63406},{"x":635148.5678852611,"z":5731544.581178385,"y":299.06075},{"x":635141.650864988,"z":5731539.610557846,"y":299.04192},{"x":635133.6490700861,"z":5731531.272389747,"y":300.09129},{"x":635131.4233905615,"z":5731529.209631696,"y":300.36232},{"x":635120.3918722782,"z":5731523.015903522,"y":300.92862},{"x":635111.1089913435,"z":5731521.209090223,"y":301.56152},{"x":635104.5736193547,"z":5731532.941112555,"y":299.78031},{"x":635095.4856326636,"z":5731544.493437337,"y":299.41092},{"x":635088.6034191557,"z":5731548.537697043,"y":300.40913},{"x":635069.5985887718,"z":5731556.151952724,"y":303.56744},{"x":635059.9839155904,"z":5731561.569692319,"y":304.01709},{"x":635041.7692930775,"z":5731570.651895206,"y":304.67625},{"x":635029.8962080037,"z":5731575.230201543,"y":305.72843},{"x":635010.417573026,"z":5731585.05762424,"y":307.15243},{"x":634991.239124583,"z":5731594.00290097,"y":309.30812},{"x":634988.1315309047,"z":5731596.479159568,"y":309.2176},{"x":634986.7983485106,"z":5731597.222428077,"y":309.31546},{"x":634978.3127935161,"z":5731601.7803001115,"y":310.01326},{"x":634963.4721450745,"z":5731616.517249734,"y":308.50882},{"x":634945.808070116,"z":5731628.28530101,"y":309.55563},{"x":634932.2239513146,"z":5731634.821094451,"y":311.32798},{"x":634928.7109256311,"z":5731636.952686115,"y":311.58957},{"x":634927.3057162003,"z":5731637.805323455,"y":311.68919},{"x":634924.2612964972,"z":5731640.505874815,"y":311.60035},{"x":634920.9078550178,"z":5731644.422259665,"y":311.17725},{"x":634908.4354823855,"z":5731653.324803321,"y":311.36372},{"x":634898.3138759527,"z":5731659.619524196,"y":311.645},{"x":634882.1696275758,"z":5731671.428466827,"y":311.38877},{"x":634870.2797019489,"z":5731679.233865776,"y":311.51004},{"x":634853.5651783304,"z":5731691.6953265965,"y":311.43443},{"x":634836.4393005681,"z":5731704.034551665,"y":311.99571},{"x":634831.5938761665,"z":5731709.469024497,"y":311.67127},{"x":634822.9711629633,"z":5731716.582964414,"y":311.93741},{"x":634817.9727538829,"z":5731722.569767388,"y":311.64025},{"x":634815.9370473542,"z":5731723.739413997,"y":311.87384},{"x":634801.8837473653,"z":5731737.496328946,"y":312.20839},{"x":634788.7588110316,"z":5731752.724777257,"y":312.39147},{"x":634773.7780433403,"z":5731767.569779956,"y":313.62774},{"x":634758.4156659814,"z":5731781.180516348,"y":315.58998},{"x":634749.7545230945,"z":5731789.740212174,"y":316.71421},{"x":634737.9593056571,"z":5731801.777155298,"y":318.45215},{"x":634724.1982547833,"z":5731817.545160901,"y":320.59146},{"x":634715.5221794582,"z":5731837.010154919,"y":320.81453},{"x":634711.5308023253,"z":5731857.0455151955,"y":319.69898},{"x":634700.1939445363,"z":5731875.215303558,"y":321.38208},{"x":634693.0591609429,"z":5731886.152808708,"y":322.57178},{"x":634685.3488118001,"z":5731900.524683864,"y":323.76726},{"x":634684.3647657896,"z":5731903.725563704,"y":323.8401},{"x":634683.4587027715,"z":5731906.594681698,"y":323.92441},{"x":634675.3532723205,"z":5731925.4072932955,"y":325.42781},{"x":634670.1761034981,"z":5731945.856117857,"y":326.51639},{"x":634666.9670204557,"z":5731959.903180822,"y":327.40234},{"x":634666.9676287002,"z":5731972.811915423,"y":327.36048},{"x":634661.261784686,"z":5731992.356362811,"y":328.93234},{"x":634652.7794356751,"z":5731994.244060439,"y":330.93259},{"x":634647.2513620142,"z":5731983.858401787,"y":332.09243},{"x":634645.3368932945,"z":5731977.909300527,"y":332.48667},{"x":634645.0123674464,"z":5731977.121655254,"y":332.54929},{"x":634645.0925904887,"z":5731974.119183772,"y":332.57665},{"x":634644.716099563,"z":5731970.10297108,"y":332.68929},{"x":634647.1356195407,"z":5731967.496849672,"y":332.29644},{"x":634646.0053559327,"z":5731963.237932582,"y":332.54029},{"x":634646.906965298,"z":5731955.360998412,"y":332.43921},{"x":634646.0210650861,"z":5731944.542970891,"y":332.71211},{"x":634647.4626498533,"z":5731924.216877233,"y":332.77565},{"x":634649.9669703399,"z":5731902.917641489,"y":333.2967},{"x":634654.8559380157,"z":5731882.906226705,"y":334.10679},{"x":634656.8018234917,"z":5731861.814636388,"y":336.53451},{"x":634655.2163999556,"z":5731840.962535654,"y":340.56514},{"x":634653.8589573049,"z":5731819.337554169,"y":345.15349},{"x":634655.0302472069,"z":5731798.7816781765,"y":349.05178},{"x":634656.1592146504,"z":5731777.223133892,"y":353.55174},{"x":634660.4237112385,"z":5731757.306319226,"y":356.64988},{"x":634666.553077098,"z":5731737.4393386375,"y":359.07739},{"x":634670.0036737561,"z":5731716.944372007,"y":363.04224},{"x":634674.4873522973,"z":5731696.588295634,"y":366.94848},{"x":634685.3862823339,"z":5731679.29699465,"y":367.83255},{"x":634697.6547800628,"z":5731662.487446487,"y":368.62552},{"x":634704.316133728,"z":5731643.413696203,"y":372.69174},{"x":634710.8483105567,"z":5731624.002654319,"y":377.37105},{"x":634727.4787403251,"z":5731612.0948901,"y":376.78897},{"x":634742.796226641,"z":5731597.592588358,"y":378.24185},{"x":634760.5534394499,"z":5731587.495564474,"y":377.85411},{"x":634772.7361610292,"z":5731573.9110678155,"y":380.88253},{"x":634783.290318592,"z":5731556.610736535,"y":386.22801},{"x":634798.87846487,"z":5731542.338394573,"y":389.22883},{"x":634818.4926336178,"z":5731535.184563153,"y":388.11958},{"x":634838.8643120135,"z":5731530.721842868,"y":385.24972},{"x":634858.325568358,"z":5731524.120481782,"y":383.1682},{"x":634871.2673989835,"z":5731518.346269481,"y":382.15939},{"x":634888.2951321463,"z":5731507.117330775,"y":381.9644},{"x":634907.218861057,"z":5731499.945354879,"y":379.14889},{"x":634918.1339230597,"z":5731495.007265673,"y":377.71873},{"x":634935.9400912266,"z":5731485.69111586,"y":375.65389},{"x":634951.1340965477,"z":5731478.41944611,"y":373.36197},{"x":634965.6433834678,"z":5731470.906920206,"y":370.7616},{"x":634966.6342127919,"z":5731470.04319503,"y":370.62941},{"x":634969.7830531491,"z":5731450.541842083,"y":372.54675},{"x":634967.126784626,"z":5731443.905058762,"y":373.99199},{"x":634966.018067258,"z":5731441.427160096,"y":374.51528},{"x":634961.9839033345,"z":5731437.201692006,"y":376.17535},{"x":634956.7302494969,"z":5731432.053316258,"y":378.21586},{"x":634942.7591571724,"z":5731416.878709591,"y":382.98045},{"x":634934.7842076735,"z":5731397.190815644,"y":384.04006},{"x":634923.3501857,"z":5731380.192394992,"y":386.17228},{"x":634914.5855205623,"z":5731361.59622198,"y":386.52774},{"x":634911.1757897218,"z":5731344.367500561,"y":384.59119},{"x":634906.0993297624,"z":5731327.428018841,"y":383.466},{"x":634905.0649616552,"z":5731322.170072569,"y":383.08427},{"x":634891.9592458731,"z":5731310.802383827,"y":387.05416},{"x":634885.3024399808,"z":5731303.836026991,"y":389.469},{"x":634886.5528172281,"z":5731295.857174755,"y":389.47028},{"x":634892.4592181618,"z":5731292.120364891,"y":388.03945},{"x":634900.798112698,"z":5731287.892253076,"y":386.53322},{"x":634906.7956801384,"z":5731288.497902976,"y":384.75171},{"x":634908.7208340131,"z":5731288.883276545,"y":384.1433},{"x":634911.7601070933,"z":5731288.964624778,"y":383.34448},{"x":634917.2407962333,"z":5731288.2210665485,"y":382.20296},{"x":634918.7961521945,"z":5731286.927313172,"y":382.21167},{"x":634922.9787035425,"z":5731283.033112865,"y":382.40161},{"x":634942.5493938891,"z":5731277.54778446,"y":379.12237},{"x":634948.2039772416,"z":5731275.4735283805,"y":377.90903},{"x":634949.7885087915,"z":5731257.599519378,"y":380.26367},{"x":634942.0627976465,"z":5731238.91984164,"y":384.55542},{"x":634938.0135078015,"z":5731222.341676495,"y":385.50249},{"x":634933.0322437335,"z":5731201.84369213,"y":385.3701},{"x":634926.516381165,"z":5731181.861047568,"y":385.6733},{"x":634922.3972905171,"z":5731162.721543169,"y":385.03034},{"x":634917.271897716,"z":5731155.351015586,"y":386.38393},{"x":634913.8227993782,"z":5731149.917156201,"y":387.22019},{"x":634911.8487287682,"z":5731146.192009996,"y":387.61582},{"x":634898.6722094696,"z":5731129.703454316,"y":391.03242},{"x":634899.122381015,"z":5731128.380116499,"y":390.70712},{"x":634888.9619784217,"z":5731115.42205363,"y":393.08418},{"x":634873.3622967098,"z":5731101.650780831,"y":397.08992},{"x":634856.3459377277,"z":5731091.7365315175,"y":401.93514},{"x":634842.5235954373,"z":5731076.121116598,"y":405.2128},{"x":634828.2480338999,"z":5731061.940287571,"y":408.553},{"x":634825.359646547,"z":5731053.628161352,"y":408.7154},{"x":634823.5265990865,"z":5731049.79554467,"y":408.92965},{"x":634810.1942049199,"z":5731036.530255281,"y":411.14315},{"x":634796.7080314795,"z":5731021.257816385,"y":412.58984},{"x":634792.0237590447,"z":5731002.548465387,"y":412.0305},{"x":634788.3740309875,"z":5730989.097036268,"y":411.97062},{"x":634786.6136715192,"z":5730987.714582724,"y":412.21033},{"x":634779.901362473,"z":5730977.631014408,"y":413.08578},{"x":634773.7246969187,"z":5730960.439731814,"y":414.15743},{"x":634771.1406233201,"z":5730956.25321289,"y":414.66086},{"x":634771.6042397949,"z":5730949.254844636,"y":414.87158},{"x":634770.5524896507,"z":5730947.223650771,"y":415.11443},{"x":634769.0409688728,"z":5730944.289909699,"y":415.46859},{"x":634761.8383569062,"z":5730931.856341371,"y":417.08911},{"x":634753.7028478344,"z":5730912.943495354,"y":419.38359},{"x":634744.7323714859,"z":5730894.230911258,"y":421.71958},{"x":634737.6775123706,"z":5730873.677754237,"y":424.25447},{"x":634733.3620264215,"z":5730854.088079577,"y":427.18012},{"x":634725.5686978175,"z":5730835.295718784,"y":430.5664},{"x":634722.8025617453,"z":5730824.983860766,"y":432.66283},{"x":634722.2944934058,"z":5730823.3010546705,"y":432.99145},{"x":634721.7351747691,"z":5730820.949187727,"y":433.45314},{"x":634721.9780787533,"z":5730819.620296584,"y":433.73633},{"x":634719.4726097697,"z":5730817.6615483435,"y":434.01681},{"x":634717.3519067834,"z":5730816.825902427,"y":434.10422},{"x":634718.012266441,"z":5730815.396885099,"y":434.39212},{"x":634718.5886869489,"z":5730814.522034078,"y":434.57706},{"x":634719.3062411093,"z":5730813.539672852,"y":434.79154},{"x":634720.7777415984,"z":5730812.8000238845,"y":435.00492},{"x":634721.7203698417,"z":5730811.155986583,"y":435.36601},{"x":634722.1497142205,"z":5730810.611051079,"y":435.4935},{"x":634723.4377478977,"z":5730808.976244779,"y":435.87916},{"x":634724.950856396,"z":5730806.679762557,"y":436.40201},{"x":634727.1183860714,"z":5730803.176669513,"y":437.17624},{"x":634729.1180370406,"z":5730800.7819094835,"y":437.73736},{"x":634732.3009841032,"z":5730798.084929345,"y":438.44884},{"x":634736.808364135,"z":5730794.978221515,"y":439.34453},{"x":634739.7870476616,"z":5730792.164504547,"y":440.01445},{"x":634747.2456601802,"z":5730784.685409827,"y":441.59944},{"x":634763.3737176378,"z":5730770.983719831,"y":444.19143},{"x":634783.4512356021,"z":5730767.291760648,"y":446.25902},{"x":634785.3253557932,"z":5730767.008021766,"y":446.42651},{"x":634807.8852734503,"z":5730768.724063156,"y":448.09703},{"x":634811.4692755345,"z":5730771.713234774,"y":448.33573},{"x":634813.3507127012,"z":5730776.326108189,"y":448.47092},{"x":634814.4448035416,"z":5730779.359979505,"y":448.55167},{"x":634815.5448406205,"z":5730782.171446222,"y":448.62954},{"x":634820.9404913778,"z":5730787.212149148,"y":448.95332},{"x":634823.6412866993,"z":5730789.6213004235,"y":449.09407},{"x":634827.7772370453,"z":5730790.065760771,"y":449.28391},{"x":634836.535678667,"z":5730790.856423117,"y":449.59469},{"x":634857.4338971426,"z":5730790.080042387,"y":449.76106},{"x":634878.7548880117,"z":5730786.4217265565,"y":449.3189},{"x":634894.5880901208,"z":5730781.169986515,"y":449.08627},{"x":634901.5217266573,"z":5730775.2350105,"y":449.38509},{"x":634904.0800766983,"z":5730772.632702282,"y":449.58757},{"x":634909.5147732017,"z":5730765.878650635,"y":450.27286},{"x":634918.3164441248,"z":5730746.973686433,"y":452.63669},{"x":634920.4501342952,"z":5730739.574892275,"y":453.55694},{"x":634921.6209198944,"z":5730737.158020885,"y":453.85553},{"x":634923.6087856921,"z":5730735.208145865,"y":454.10773},{"x":634925.1821609609,"z":5730733.247178187,"y":454.34875},{"x":634928.8095132189,"z":5730729.449389285,"y":454.80074},{"x":634947.1292870188,"z":5730721.704869254,"y":455.49946},{"x":634959.7332357378,"z":5730726.048424147,"y":454.7956},{"x":634963.5732835531,"z":5730732.383023456,"y":454.09151},{"x":634974.6604085127,"z":5730749.483452404,"y":452.11164},{"x":634984.5432932938,"z":5730767.664485908,"y":450.24766},{"x":634995.1050049735,"z":5730786.308848669,"y":448.80424},{"x":635008.3512765359,"z":5730802.799488892,"y":448.10412},{"x":635016.3419379959,"z":5730821.931460112,"y":447.46629},{"x":635020.3133714183,"z":5730838.841434808,"y":447.04636},{"x":635018.7804404623,"z":5730847.035258106,"y":446.79757},{"x":635015.2370678906,"z":5730850.278820795,"y":446.61189},{"x":635004.2692855289,"z":5730867.456384511,"y":446.13231},{"x":634992.8990063831,"z":5730884.178062421,"y":445.90748},{"x":634980.4163782903,"z":5730895.973564188,"y":445.80672},{"x":634963.8855084298,"z":5730909.218658997,"y":445.78375},{"x":634947.8323273528,"z":5730922.69915642,"y":445.21412},{"x":634939.2678082206,"z":5730940.497593613,"y":443.04125},{"x":634929.6731148455,"z":5730958.045904604,"y":439.00898},{"x":634930.0852305692,"z":5730960.727706174,"y":438.4435},{"x":634943.5140193437,"z":5730975.553845559,"y":436.85755},{"x":634958.5071123373,"z":5730988.752672741,"y":436.14283},{"x":634970.3022774896,"z":5731005.204386867,"y":434.21694},{"x":634982.6440322455,"z":5731021.893333105,"y":432.18275},{"x":634997.2617115899,"z":5731036.195055967,"y":430.9352},{"x":635012.1764668326,"z":5731049.725806507,"y":429.62407},{"x":635026.7731287737,"z":5731064.806035262,"y":427.52887},{"x":635043.969692272,"z":5731075.727237045,"y":426.84509},{"x":635059.6112782268,"z":5731090.501716195,"y":424.7225},{"x":635075.4356237225,"z":5731103.61191142,"y":423.24814},{"x":635091.5510951759,"z":5731116.173550867,"y":421.96285},{"x":635108.3572527716,"z":5731128.753758345,"y":420.76836},{"x":635126.3763801063,"z":5731139.919871661,"y":420.20014},{"x":635147.6762893883,"z":5731142.160144353,"y":421.79867},{"x":635168.7446074544,"z":5731142.725061882,"y":423.19024},{"x":635188.7499361957,"z":5731144.263099934,"y":424.07821},{"x":635209.5628227148,"z":5731144.042360938,"y":425.02058},{"x":635228.4975766465,"z":5731154.565717335,"y":425.03821},{"x":635243.9938154778,"z":5731166.999973119,"y":425.18473},{"x":635239.4593081073,"z":5731186.575303505,"y":423.97364},{"x":635235.9341130456,"z":5731207.179258465,"y":422.62905},{"x":635242.1634764797,"z":5731227.488518149,"y":422.2683},{"x":635252.4703049521,"z":5731242.67692207,"y":422.58928},{"x":635252.8156804543,"z":5731242.686189598,"y":422.6264},{"x":635249.0514619641,"z":5731236.130801737,"y":422.57637},{"x":635259.3407876687,"z":5731254.54594386,"y":422.64683},{"x":635272.966510318,"z":5731272.271672758,"y":423.10603},{"x":635281.434997949,"z":5731286.409266089,"y":423.26043},{"x":635293.2676056467,"z":5731303.975649475,"y":423.60629},{"x":635306.1238825726,"z":5731319.455176271,"y":423.83789},{"x":635317.749099864,"z":5731337.016057854,"y":422.76484},{"x":635323.8620591168,"z":5731346.194063037,"y":421.49163},{"x":635326.87782019,"z":5731349.7247912185,"y":420.8098},{"x":635337.9712043706,"z":5731366.4924692735,"y":416.38895},{"x":635347.94142394,"z":5731383.89771013,"y":409.93217},{"x":635357.6983797634,"z":5731401.519812123,"y":401.6596},{"x":635358.397394717,"z":5731416.673018863,"y":396.05167},{"x":635358.5030746099,"z":5731420.459465626,"y":394.6227},{"x":635359.809867042,"z":5731423.2766259,"y":393.09621},{"x":635358.4138667879,"z":5731426.35504813,"y":392.45565},{"x":635355.412439143,"z":5731437.736551932,"y":389.28363},{"x":635349.4390936168,"z":5731456.82803025,"y":384.30417},{"x":635344.0064192375,"z":5731476.379163539,"y":378.97574},{"x":635346.0263812892,"z":5731488.674493574,"y":373.48083},{"x":635347.5769861607,"z":5731495.281807602,"y":370.28869},{"x":635347.6311265454,"z":5731495.839674562,"y":370.05141},{"x":635347.3548399357,"z":5731495.832255106,"y":370.17706},{"x":635345.3961660552,"z":5731491.550917747,"y":372.65581},{"x":635347.2603258095,"z":5731486.481977678,"y":373.79181},{"x":635347.6023102911,"z":5731484.0429439405,"y":374.57971},{"x":635347.6108807452,"z":5731481.14982624,"y":375.6857},{"x":635347.0579172671,"z":5731478.575476936,"y":376.90425},{"x":635346.7454062206,"z":5731477.342976098,"y":377.50525},{"x":635346.4713265462,"z":5731472.105333465,"y":379.62066},{"x":635346.6423188056,"z":5731470.885816585,"y":380.0186},{"x":635346.7412529056,"z":5731469.775647281,"y":380.4041},{"x":635349.9409045283,"z":5731458.733310351,"y":383.36959},{"x":635350.8294962288,"z":5731456.531520838,"y":383.86275},{"x":635351.5739715943,"z":5731454.548426477,"y":384.32951},{"x":635358.9287770349,"z":5731435.494050518,"y":388.77129},{"x":635360.5861331746,"z":5731432.97906057,"y":389.0959},{"x":635360.6850705061,"z":5731431.8688915325,"y":389.48721},{"x":635360.7059758736,"z":5731431.090474688,"y":389.77995},{"x":635360.0032175002,"z":5731410.929448962,"y":397.58582},{"x":635359.8332832424,"z":5731399.240211572,"y":401.78492},{"x":635358.9861034942,"z":5731397.325655675,"y":402.70308},{"x":635349.5932080394,"z":5731384.164631477,"y":409.46415},{"x":635345.7537920123,"z":5731375.270206174,"y":412.83447},{"x":635344.8315568826,"z":5731373.576202863,"y":413.46963},{"x":635336.1173686956,"z":5731360.87856315,"y":417.88904},{"x":635329.8893851244,"z":5731345.68819422,"y":421.29505},{"x":635337.1622281974,"z":5731339.985494693,"y":421.70226},{"x":635355.1407570948,"z":5731329.451288538,"y":421.96091},{"x":635371.6594646631,"z":5731316.652284039,"y":423.12705},{"x":635388.1573472931,"z":5731304.631749172,"y":424.61896},{"x":635403.9884626998,"z":5731291.703092212,"y":426.49499},{"x":635420.3692685068,"z":5731278.900532694,"y":428.0655},{"x":635435.6207050135,"z":5731264.398437312,"y":429.12618},{"x":635453.2931861966,"z":5731252.409663503,"y":428.89207},{"x":635469.4460979901,"z":5731240.380107724,"y":427.77889},{"x":635483.5809568394,"z":5731228.852770591,"y":425.97169},{"x":635498.3794099527,"z":5731215.785351152,"y":423.19326},{"x":635500.487547962,"z":5731214.506629489,"y":422.79388},{"x":635504.3464915858,"z":5731212.3847133815,"y":422.064},{"x":635521.5327997594,"z":5731200.494377639,"y":418.23174},{"x":635537.6498566917,"z":5731187.239952848,"y":413.9611},{"x":635552.2861994933,"z":5731172.499080832,"y":409.4373},{"x":635565.7818055555,"z":5731161.622464599,"y":405.56027},{"x":635572.8906808952,"z":5731162.036225517,"y":404.53092},{"x":635594.0489614899,"z":5731161.826363934,"y":400.87928},{"x":635605.8251069239,"z":5731163.478552022,"y":398.88553},{"x":635606.82535113,"z":5731164.8408547975,"y":398.95597},{"x":635606.8884440751,"z":5731165.065117763,"y":398.98907},{"x":635604.816156701,"z":5731165.009367889,"y":399.40878},{"x":635608.8435208108,"z":5731164.338735569,"y":398.42606},{"x":635609.7445038529,"z":5731164.251692149,"y":398.21576},{"x":635611.6696637878,"z":5731164.637334157,"y":397.87932},{"x":635612.6427148799,"z":5731164.440947352,"y":397.62663},{"x":635614.0963080544,"z":5731164.368772115,"y":397.29235},{"x":635615.4868087113,"z":5731164.072334215,"y":396.92353},{"x":635623.9320646704,"z":5731163.631859659,"y":394.91386},{"x":635625.2956377118,"z":5731164.336245227,"y":394.74146},{"x":635628.25694051,"z":5731164.74977263,"y":394.13709},{"x":635629.6294891463,"z":5731165.1205524625,"y":393.89209},{"x":635637.2640373011,"z":5731166.550094369,"y":392.39603},{"x":635644.1088184874,"z":5731169.071223489,"y":391.32232},{"x":635646.7608947472,"z":5731170.700551782,"y":391.04518},{"x":635647.9922956864,"z":5731171.17882119,"y":390.8563},{"x":635649.3558635428,"z":5731171.883213364,"y":390.68444},{"x":635652.1580596006,"z":5731173.071453194,"y":390.27359},{"x":635656.1916537461,"z":5731174.737966046,"y":389.66114},{"x":635658.9938467292,"z":5731175.926209734,"y":389.22755},{"x":635662.5980155251,"z":5731178.137584964,"y":388.78849},{"x":635663.8925034986,"z":5731178.840122028,"y":388.60363},{"x":635684.3454633215,"z":5731184.287085242,"y":384.77954},{"x":635704.4651957573,"z":5731191.839537012,"y":382.72456},{"x":635718.7850766408,"z":5731194.005609032,"y":381.00151},{"x":635739.0364860849,"z":5731196.665299213,"y":377.88312},{"x":635758.615279807,"z":5731201.19876598,"y":375.04382},{"x":635778.7945749108,"z":5731203.967958566,"y":371.90341},{"x":635799.1000190182,"z":5731207.18576336,"y":368.93414},{"x":635819.1048487549,"z":5731206.166796535,"y":364.87679},{"x":635839.0197856769,"z":5731208.483976904,"y":361.11396},{"x":635847.7294628783,"z":5731211.055647021,"y":359.59551},{"x":635867.0589297691,"z":5731217.140784372,"y":356.29848},{"x":635886.3433847248,"z":5731224.894030505,"y":352.95249},{"x":635901.4956014887,"z":5731239.769339748,"y":351.90121},{"x":635917.5395992409,"z":5731252.331800367,"y":350.33514},{"x":635935.973953658,"z":5731260.8413046645,"y":346.64128},{"x":635955.93371915,"z":5731264.050432426,"y":340.27},{"x":635976.6381328499,"z":5731262.717118565,"y":331.702},{"x":635992.0510647169,"z":5731270.477626544,"y":326.20165},{"x":635994.7901255852,"z":5731274.001306272,"y":325.26247},{"x":635996.090546223,"z":5731274.481525417,"y":324.6747},{"x":635997.0576604139,"z":5731277.06713257,"y":324.38372},{"x":635998.6164424053,"z":5731280.781535944,"y":323.78573},{"x":636001.8874676181,"z":5731300.455637305,"y":321.93269},{"x":636001.7853877346,"z":5731301.676998178,"y":321.94104},{"x":636001.8154557883,"z":5731303.12449111,"y":321.86294},{"x":636003.248078263,"z":5731306.390359696,"y":320.89899},{"x":636004.8639172775,"z":5731310.551438162,"y":319.74919},{"x":636005.2157760934,"z":5731330.814476426,"y":318.28527},{"x":636003.8706059293,"z":5731342.240350298,"y":318.3298},{"x":636006.0120160251,"z":5731347.417160418,"y":316.73437},{"x":636006.4895906895,"z":5731350.212127487,"y":316.26855},{"x":636008.012331301,"z":5731355.260961625,"y":315.03187},{"x":636008.9794785226,"z":5731360.406087332,"y":314.11141},{"x":636011.5534879826,"z":5731372.6054170905,"y":311.73216},{"x":636012.142196013,"z":5731376.404933016,"y":311.11197},{"x":636010.0883889713,"z":5731393.598411559,"y":311.1829},{"x":636013.6655658452,"z":5731412.167958757,"y":307.88687},{"x":636014.061998341,"z":5731412.84635616,"y":307.6172},{"x":636014.7857900733,"z":5731414.201287073,"y":307.11763},{"x":636016.6988769297,"z":5731417.591410875,"y":305.80999},{"x":636017.7350209663,"z":5731420.178887163,"y":305.05866},{"x":636018.9213134184,"z":5731422.3252827665,"y":304.25399},{"x":636032.0755057208,"z":5731442.043575416,"y":296.0164},{"x":636037.1869942426,"z":5731449.860079888,"y":293.11411},{"x":636044.6138724019,"z":5731456.403687845,"y":289.42596},{"x":636046.8272586683,"z":5731461.471179784,"y":288.20704},{"x":636049.5962853961,"z":5731471.561419067,"y":286.52228},{"x":636049.4911927385,"z":5731472.893981654,"y":286.49446},{"x":636050.1548984984,"z":5731473.91344681,"y":286.1667},{"x":636050.5062947572,"z":5731476.259881142,"y":285.8945},{"x":636050.551352945,"z":5731477.151363688,"y":285.82657},{"x":636050.5814344168,"z":5731481.158373915,"y":285.58836},{"x":636050.7586329996,"z":5731482.2759899795,"y":285.45418},{"x":636054.3564404825,"z":5731487.269573659,"y":283.70966},{"x":636053.0021996673,"z":5731501.588561335,"y":283.54856},{"x":636054.2124706462,"z":5731502.845347976,"y":283.03914},{"x":636055.6930240678,"z":5731504.331997723,"y":282.42508},{"x":636057.9153807887,"z":5731509.065888621,"y":281.47049},{"x":636059.0926271281,"z":5731511.545901357,"y":281.01862},{"x":636060.1166932136,"z":5731512.018679816,"y":280.66287},{"x":636061.1437611182,"z":5731512.380256231,"y":280.31629},{"x":636063.5162358828,"z":5731514.113553423,"y":279.55932},{"x":636067.1049775432,"z":5731516.8812371185,"y":278.55712},{"x":636070.08105772,"z":5731516.739016967,"y":277.72144},{"x":636072.7838542669,"z":5731516.478137066,"y":277.00496},{"x":636074.7809242005,"z":5731516.75462147,"y":276.54241},{"x":636075.741921001,"z":5731517.003133799,"y":276.33348},{"x":636077.6158594228,"z":5731516.719878348,"y":275.872},{"x":636078.3215867018,"z":5731516.182515879,"y":275.67837},{"x":636078.9582425819,"z":5731515.643288615,"y":275.5141},{"x":636079.5198222148,"z":5731515.3246010365,"y":275.38538},{"x":636079.9312491156,"z":5731515.44699272,"y":275.31797},{"x":636080.0363497477,"z":5731514.114430569,"y":275.19603},{"x":636079.9672781772,"z":5731514.112565661,"y":275.20913},{"x":636079.1774505686,"z":5731512.64455752,"y":275.25073},{"x":636078.8651189595,"z":5731511.412008245,"y":275.22522},{"x":636078.8170641027,"z":5731510.631727571,"y":275.18184},{"x":636078.889138115,"z":5731510.522390208,"y":275.15978},{"x":636079.1684269934,"z":5731510.41864753,"y":275.0969},{"x":636079.3065702354,"z":5731510.422377323,"y":275.07002},{"x":636079.8591432027,"z":5731510.437296539,"y":274.96422},{"x":636079.9252124064,"z":5731510.5503637,"y":274.95902},{"x":636078.9702193176,"z":5731510.079446081,"y":275.11382},{"x":636077.3365191717,"z":5731509.145070875,"y":275.4299},{"x":636080.5888910085,"z":5731509.01031634,"y":274.72991},{"x":636082.039395459,"z":5731509.04947977,"y":274.40252},{"x":636080.5648715649,"z":5731509.899934371,"y":274.79075},{"x":636079.3636322361,"z":5731510.86905124,"y":275.08898},{"x":636079.0843433779,"z":5731510.972793907,"y":275.15095},{"x":636078.9401953589,"z":5731511.191468628,"y":275.19479},{"x":636079.1534149912,"z":5731510.974658803,"y":275.13739},{"x":636080.252540073,"z":5731508.667385012,"y":274.7744},{"x":636076.5887226907,"z":5731506.120231617,"y":275.42336},{"x":636082.4238005846,"z":5731510.172691933,"y":274.35798},{"x":636082.2586351132,"z":5731511.1697823405,"y":274.46728},{"x":636081.7150695926,"z":5731510.821256098,"y":274.59247},{"x":636081.8532128247,"z":5731510.824985963,"y":274.55722},{"x":636081.2315528805,"z":5731508.248684839,"y":274.55066},{"x":636081.3666937363,"z":5731508.363616943,"y":274.52747},{"x":636081.2976220867,"z":5731508.361752018,"y":274.54274},{"x":636082.3577314299,"z":5731510.059624739,"y":274.37103},{"x":636082.6640131262,"z":5731503.836028443,"y":273.96567},{"x":636082.5258547075,"z":5731501.272781809,"y":273.86682},{"x":636082.492812525,"z":5731499.936489842,"y":273.81305},{"x":636082.1924905307,"z":5731498.259131373,"y":273.8128},{"x":636081.6459054594,"z":5731495.4622907005,"y":273.76229},{"x":636086.7150635216,"z":5731474.121478851,"y":269.57076},{"x":636087.165512966,"z":5731470.238725169,"y":269.37974},{"x":636086.9762976693,"z":5731467.006400037,"y":269.38601},{"x":636086.4327131264,"z":5731464.098356732,"y":269.4604},{"x":636086.2014617327,"z":5731462.422863109,"y":269.46375},{"x":636086.0392824501,"z":5731460.749234481,"y":269.43966},{"x":636085.2464141024,"z":5731454.273394633,"y":269.47373},{"x":636084.8409715423,"z":5731451.369081524,"y":269.61013},{"x":636083.9700357718,"z":5731447.784500345,"y":269.95857},{"x":636084.1622085402,"z":5731443.227073291,"y":269.98226},{"x":636082.705593976,"z":5731430.612731466,"y":271.33108},{"x":636082.231056452,"z":5731425.14703732,"y":271.57814},{"x":636082.7445899402,"z":5731424.048069358,"y":271.49849},{"x":636083.1289852028,"z":5731422.611764864,"y":271.41485},{"x":636082.7174054217,"z":5731402.01324162,"y":269.51342},{"x":636083.3359124219,"z":5731381.665097276,"y":268.74298},{"x":636082.3897830644,"z":5731365.503475064,"y":269.13379},{"x":636082.5519289484,"z":5731362.058070766,"y":269.36464},{"x":636082.5759475937,"z":5731361.168452909,"y":269.45207},{"x":636081.7590522892,"z":5731358.141748913,"y":270.08099},{"x":636085.7861926395,"z":5731336.995369095,"y":272.36497},{"x":636085.1012970909,"z":5731316.278186063,"y":275.48715},{"x":636085.6087338545,"z":5731302.604042384,"y":276.65},{"x":636086.0291648984,"z":5731299.833311513,"y":276.71708},{"x":636087.9151737103,"z":5731296.545733661,"y":276.19153},{"x":636088.8070994664,"z":5731291.67335063,"y":276.21533},{"x":636090.224583395,"z":5731285.257191633,"y":276.12287},{"x":636098.1530399623,"z":5731265.5515549,"y":274.36107},{"x":636108.276936451,"z":5731243.9021121515,"y":272.37872},{"x":636110.7906620202,"z":5731240.408925238,"y":271.85241},{"x":636116.0704013808,"z":5731234.319634042,"y":270.69734},{"x":636127.6720529548,"z":5731216.827613413,"y":270.9794},{"x":636136.1773739932,"z":5731209.044921129,"y":271.73756},{"x":636148.3197133037,"z":5731202.250745025,"y":266.96189},{"x":636167.2825982444,"z":5731193.749026916,"y":266.57497},{"x":636177.9984103286,"z":5731191.145150051,"y":266.64939},{"x":636182.8547623272,"z":5731190.497369474,"y":266.65582},{"x":636203.89290258,"z":5731192.17863958,"y":266.70398},{"x":636224.5617018967,"z":5731189.621247325,"y":266.82222},{"x":636244.6239809897,"z":5731181.372090795,"y":266.41151},{"x":636265.7946209279,"z":5731170.482171706,"y":265.41329},{"x":636269.0712706797,"z":5731169.457917788,"y":265.28517},{"x":636288.5362273263,"z":5731155.18347506,"y":265.0339},{"x":636305.4844615341,"z":5731141.953881927,"y":265.43759},{"x":636311.82457241,"z":5731140.122227269,"y":266.84292},{"x":636322.2433187302,"z":5731135.730079609,"y":272.96839},{"x":636323.847122574,"z":5731135.217036387,"y":273.97847},{"x":636337.5664410231,"z":5731134.030121273,"y":277.49137},{"x":636348.4565177715,"z":5731135.214949644,"y":279.42487},{"x":636354.351893531,"z":5731139.6031939965,"y":278.8853},{"x":636358.7215550741,"z":5731144.172739333,"y":276.48679},{"x":636362.5326929776,"z":5731146.3902254375,"y":276.8759},{"x":636366.6921028844,"z":5731151.065374001,"y":275.47504},{"x":636368.9325213657,"z":5731152.572671173,"y":275.10375},{"x":636381.6091457595,"z":5731161.818321285,"y":273.59083},{"x":636384.4441639645,"z":5731164.343265439,"y":272.53686},{"x":636388.639645098,"z":5731167.68400717,"y":272.25261},{"x":636391.8680518405,"z":5731170.998584955,"y":271.58553},{"x":636399.3276277264,"z":5731183.998045033,"y":267.15479},{"x":636409.1626918147,"z":5731198.619773475,"y":264.57074},{"x":636419.0581788272,"z":5731205.898442582,"y":264.72991},{"x":636427.2294540268,"z":5731218.138226566,"y":264.8832},{"x":636427.9682181554,"z":5731218.937207143,"y":264.89841},{"x":636428.8270744497,"z":5731220.40713987,"y":264.78786},{"x":636431.4128216382,"z":5731221.923813898,"y":265.07181},{"x":636450.3089636047,"z":5731231.2267135205,"y":268.00606},{"x":636454.49531362,"z":5731234.901118411,"y":267.83211},{"x":636454.4621991267,"z":5731236.124341829,"y":267.66309},{"x":636452.8612586991,"z":5731239.085660072,"y":267.12054},{"x":636451.6538625931,"z":5731240.2770944,"y":266.84576},{"x":636450.5185527694,"z":5731241.359196802,"y":266.57218},{"x":636449.1069419091,"z":5731242.433819825,"y":266.22425},{"x":636447.9656125627,"z":5731243.738327048,"y":265.81754},{"x":636445.7460104732,"z":5731246.571616375,"y":264.87149},{"x":636442.715568383,"z":5731248.715255954,"y":264.1092},{"x":636441.2439163376,"z":5731249.45440491,"y":263.90739},{"x":636439.9104152767,"z":5731250.197293849,"y":263.76953},{"x":636438.3636686972,"z":5731251.156978122,"y":263.67026},{"x":636431.6630626601,"z":5731256.094653535,"y":264.06947},{"x":636430.3235450103,"z":5731257.059949236,"y":264.22519},{"x":636428.9119428471,"z":5731258.134577793,"y":264.36001},{"x":636427.5003412857,"z":5731259.209206736,"y":264.45626},{"x":636426.0226750016,"z":5731260.170764334,"y":264.51052},{"x":636423.2745694522,"z":5731262.099489465,"y":264.55836},{"x":636418.1297592138,"z":5731265.743887264,"y":264.51517},{"x":636416.7992755607,"z":5731266.375580063,"y":264.50817},{"x":636414.3304865856,"z":5731268.200585708,"y":264.50753},{"x":636413.2672755171,"z":5731269.173363593,"y":264.50923},{"x":636411.0087236125,"z":5731270.89277695,"y":264.51316},{"x":636405.2061445841,"z":5731275.854788927,"y":264.54521},{"x":636404.2210397832,"z":5731276.495831546,"y":264.55767},{"x":636401.1636884309,"z":5731277.080796261,"y":264.62327},{"x":636381.2277381476,"z":5731283.2183570145,"y":265.65717},{"x":636375.2512003846,"z":5731284.392053759,"y":266.24815},{"x":636358.946307258,"z":5731289.181258019,"y":268.55452},{"x":636359.769187128,"z":5731289.426086563,"y":268.43003}]},"bbox":[[10.949362,51.711183],[10.976243,51.722689]],"season":{"jan":"no","feb":"no","mar":"no","apr":"no","may":"no","jun":"no","jul":"no","aug":"no","sep":"no","oct":"no","nov":"no","dec":"no"},"metrics":{"duration":{"minimal":167.0},"elevation":{"elevationProfile":{"url":"https://www.outdooractive.com/api/v2/project/oad-harz/tour/23600430/export/elpro?key=IKLXEIKF-EMWGMGHI-4OSSNPLY","fallbackUrl":"https://www.outdooractive.com/api/v2/project/oad-harz/tour/23600430/export/elpro?type=png&key=IKLXEIKF-EMWGMGHI-4OSSNPLY"},"ascent":256,"descent":250,"minAltitude":264,"maxAltitude":455},"length":8260},"ratingInfo":{"stamina":0,"difficulty":0,"landscape":0,"experience":0},"wayTypeInfo":{"legend":[{"type":"unknown","title":"Unbekannt","length":8260.3324,"color":"#ababab"}]},"teaserText":"Terrainkurweg 19","isWinter":false,"openState":"unknown","isClosedByClosure":false,"isIgnoreClosedByClosure":false}]}}