{"header":{"status":"ok"},"answer":{"type":"oois","contents":[{"type":"tour","id":"6328796","title":"Vom Hexentanzplatz nach Wendefurth","category":{"id":"21896072","ooiType":"tour","title":"Wanderung","icon":{"url":"https://res0.oastatic.com/icons/oa/hiking/raspberry_wine/hiking.square_vector.svg","color":"#b33451"},"iconMap":{"url":"https://res0.oastatic.com/icons/oa/hiking/raspberry_wine/hiking.map_vector.svg"},"iconTransparent":{"url":"https://res0.oastatic.com/icons/oa/hiking/hiking.transparent.svg"},"strokeColor":"#b33451","mapOverlays":["hiking"],"keys":["hikingTourTrail"]},"primaryImage":{"id":"51498409","meta":{"author":{"id":"1104"},"source":{"name":"Elbe Medien Produktion GmbH, Archiv TSB"},"system":{"createdIn":"12","lastModifiedIn":"12"},"timestamp":{"createdAt":"2020-07-16T02:03:10Z","lastModifiedAt":"2024-01-17T13:38:02Z","changedByClientAt":"2020-09-01T12:19:17Z","firstPublishedAt":"2020-07-16T02:04:54Z"},"license":{"type":"valueHelpText","id":"16925726","url":"https://creativecommons.org/licenses/by/4.0/deed.de","short":"CC BY"},"ranking":55,"translations":["de"],"externalInfo":{"id":"img_p_100048936_2","system":"ict-harz-poi"},"workflow":"published"},"title":"Informationszentrum Talsperre Wendefurth"},"images":[{"type":"image","id":"51498409","relations":["isPrimary","isGallery"],"primaryImage":{"id":"51498409","meta":{"author":{"id":"1104"},"source":{"name":"Elbe Medien Produktion GmbH, Archiv TSB"},"system":{"createdIn":"12","lastModifiedIn":"12"},"timestamp":{"createdAt":"2020-07-16T02:03:10Z","lastModifiedAt":"2024-01-17T13:38:02Z","changedByClientAt":"2020-09-01T12:19:17Z","firstPublishedAt":"2020-07-16T02:04:54Z"},"license":{"type":"valueHelpText","id":"16925726","url":"https://creativecommons.org/licenses/by/4.0/deed.de","short":"CC BY"},"ranking":55,"translations":["de"],"externalInfo":{"id":"img_p_100048936_2","system":"ict-harz-poi"},"workflow":"published"},"title":"Informationszentrum Talsperre Wendefurth"},"meta":{"author":{"id":"1104"},"source":{"name":"Elbe Medien Produktion GmbH, Archiv TSB"},"system":{"createdIn":"12","lastModifiedIn":"12"},"timestamp":{"createdAt":"2020-07-16T02:03:10Z","lastModifiedAt":"2024-01-17T13:38:02Z","changedByClientAt":"2020-09-01T12:19:17Z","firstPublishedAt":"2020-07-16T02:04:54Z"},"license":{"type":"valueHelpText","id":"16925726","url":"https://creativecommons.org/licenses/by/4.0/deed.de","short":"CC BY"},"ranking":55,"workflow":"published"},"point":[10.922813,51.742124],"sourceImageInfo":{"width":3000,"height":1686},"title":"Informationszentrum Talsperre Wendefurth","isValidImage":true},{"type":"image","id":"23182577","relations":["isGallery"],"primaryImage":{"id":"23182577"},"meta":{"author":{"name":"Michael Hesse"},"source":{"name":"Bodetal Tourismus GmbH"},"system":{"createdIn":"12","lastModifiedIn":"12"},"timestamp":{"createdAt":"2017-06-08T10:03:13Z","lastModifiedAt":"2022-10-28T08:16:21Z","changedByClientAt":"2022-10-28T08:16:21Z","firstPublishedAt":"2017-06-08T10:03:13Z"},"ranking":5,"workflow":"published"},"sourceImageInfo":{"width":960,"height":640},"title":"Blick aus der Kabinenbahn ins Bodetal","isValidImage":true},{"type":"image","id":"6328820","relations":["isGallery"],"primaryImage":{"id":"6328820"},"meta":{"author":{"name":"Michael Hesse"},"source":{"name":"Bodetal Tourismus GmbH"},"system":{"createdIn":"12","lastModifiedIn":"12"},"timestamp":{"createdAt":"2013-03-15T12:13:43Z","lastModifiedAt":"2022-10-28T08:16:21Z","changedByClientAt":"2022-10-28T08:16:21Z","firstPublishedAt":"2022-10-28T08:16:21Z"},"ranking":5,"workflow":"published"},"sourceImageInfo":{"width":960,"height":640},"title":"Furt in Treseburg","isValidImage":true},{"type":"image","id":"23182579","relations":["isGallery"],"primaryImage":{"id":"23182579"},"meta":{"author":{"name":"Michael Hesse"},"source":{"name":"Bodetal Tourismus GmbH"},"system":{"createdIn":"12","lastModifiedIn":"12"},"timestamp":{"createdAt":"2017-06-08T10:03:13Z","lastModifiedAt":"2022-10-28T08:16:21Z","changedByClientAt":"2022-10-28T08:16:21Z","firstPublishedAt":"2017-06-08T10:03:13Z"},"ranking":5,"workflow":"published"},"sourceImageInfo":{"width":960,"height":640},"title":"Waldbühne Altenbrak","isValidImage":true},{"type":"image","id":"23182578","relations":["isGallery"],"primaryImage":{"id":"23182578"},"meta":{"author":{"name":"Udo Stieglitz"},"source":{"name":"Bodetal Tourismus GmbH"},"system":{"createdIn":"12","lastModifiedIn":"12"},"timestamp":{"createdAt":"2017-06-08T10:03:13Z","lastModifiedAt":"2022-10-28T08:16:21Z","changedByClientAt":"2022-10-28T08:16:21Z","firstPublishedAt":"2017-06-08T10:03:13Z"},"ranking":5,"workflow":"published"},"sourceImageInfo":{"width":640,"height":960},"title":"Talsperre in Wendefurth","isValidImage":true},{"type":"image","id":"50773301","relations":["isGallery"],"primaryImage":{"id":"50773301"},"meta":{"author":{"id":"1045430","profileImageId":"21897044"},"source":{"name":"Hexenhaus Thale GmbH"},"system":{"createdIn":"12","lastModifiedIn":"401398"},"timestamp":{"createdAt":"2020-06-22T16:16:07Z","lastModifiedAt":"2023-05-26T21:57:09Z","changedByClientAt":"2023-03-11T12:50:01Z","firstPublishedAt":"2020-06-22T16:17:15Z"},"license":{"type":"valueHelpText","id":"16925726","url":"https://creativecommons.org/licenses/by/4.0/deed.de","short":"CC BY"},"ranking":55,"workflow":"published"},"point":[11.024694,51.731667],"sourceImageInfo":{"width":3504,"height":2336},"title":"Hexenhaus Thale","isValidImage":true},{"type":"image","id":"50773288","relations":["isGallery"],"primaryImage":{"id":"50773288"},"meta":{"source":{"name":"E.Klinger"},"system":{"createdIn":"12","lastModifiedIn":"12"},"timestamp":{"createdAt":"2020-06-22T16:16:05Z","lastModifiedAt":"2023-05-26T21:57:11Z","changedByClientAt":"2020-06-22T16:16:05Z","firstPublishedAt":"2020-06-22T16:17:14Z"},"license":{"type":"valueHelpText","id":"16925726","url":"https://creativecommons.org/licenses/by/4.0/deed.de","short":"CC BY"},"ranking":65,"workflow":"published"},"point":[10.916419,51.740689],"sourceImageInfo":{"width":4554,"height":2761},"title":"Floß Wendefurth","isValidImage":true}],"meta":{"author":{"id":"6080118","name":"Harzer Tourismusverband","profileImageId":"25527429","workflow":"published"},"source":{"type":"organisation","id":"1479238","logo":{"type":"image","id":"1962302","title":"Harz: Magische Gebirgswelt"},"labels":["verified","badgeExplorersChoice"],"name":"Harz: Magische Gebirgswelt","url":"http://www.harzinfo.de/","workflow":"published"},"system":{"createdIn":"12","lastModifiedIn":"12"},"timestamp":{"createdAt":"2013-03-15T11:57:27Z","lastModifiedAt":"2024-03-11T11:25:36Z","changedByClientAt":"2022-10-28T08:23:46Z","firstPublishedAt":"2013-03-15T12:15:35Z"},"license":{"type":"valueHelpText","id":"16925727","url":"https://creativecommons.org/licenses/by-sa/4.0/deed.de","short":"CC BY-SA"},"ranking":95,"translations":["de"],"workflow":"published"},"texts":{"short":"<p>Hexentanzplatz – Treseburg – Altenbrak – Wendefurth (ca. 16 km)</p>","long":"<p>Diese Tour führt Sie vom sagenumwobenen Hexentanzplatz oberhalb des Bodetals entlang nach Treseburg. Über Altenbrak gelangen Sie nach Wendefurth, wo Sie das Talsperren-Informationszentrum besuchen oder einen Ruderbootausflug auf dem Stausee unternehmen können.</p>","directions":"<p>Diese Wanderung beginnt am zentralen Wanderwegschilderbaum auf dem Hexentanzplatz. Von hier geht es der Markierung mit dem roten Punkt folgend auf ebenen Wegen vorbei am Tierpark mit einem Abstecher zum Aussichtspunkt »La Viershöhe« (Blick ins Bodetal, Stempelstelle der Harzer Wandernadel).</p>\r\n<p>Der Weg führt weiter vorbei am Pfeilsdenkmal zum Aussichtspunkt »Weißer Hirsch« (Blick auf Treseburg) und von dort steil abwärts in das Luppbodetal. Kurz darauf erreichen Sie Treseburg, wo Sie flussaufwärts der Ausschilderung des Harzer Hexen-Stiegs nach Altenbrak folgen. Vom Ortsrand Altenbrak verläuft der Wanderweg zwischen der Gaststätte »Jägerbaude« und der Pension »Harzresidenz« über den Osterberg zum Großparkplatz in der Ortsmitte.</p>\r\n<p>Von hier wiederum der Markierung mit der grünen Hexe folgend kommen Sie vorbei an historischen Altbergbauwerken, unterqueren eine historische Wasserbrücke, passieren eine Forellenaufzuchtanlage mit Einkehrmöglichkeit und erreichen dann den Ort Wendefurth. Die Bundesstraße 81 überquerend gelangen Sie zur Wendfurther Talsperre.</p>","publicTransit":"<p>Bahnhof und Busbahnhof in Thale, von dort der Aufstieg oder mit der Seilbahn zum Hexentanzplatz</p>","gettingThere":"<p>A36 Abfahrt Thale, weiter über die L240 über Warnstedt nach Thale, dort weiter in Richtung Hexentanzplatz</p>","parking":"<p>Parkplatz auf dem Hexentanzplatz (gebührenpflichtig)</p>","startingPoint":"Parkplatz auf dem Hexentanzplatz, Hexentanzplatz, 06502 Thale","additionalInformation":"<p>Bodetal-Information THALE<br/>Bahnhofstraße 1<br/>06502 Thale<br/>Tel. 03947 776800<br/><a href=\"http://www.bodetal.de\">info@bodetal.de<br/>www.bodetal.de</a></p>","destination":"Wendefurth"},"point":{"x":639869.968786782,"z":5733209.163192096,"y":448.0},"labels":["top"],"primaryRegion":{"type":"tourismarea","id":"1043712","title":"Harz"},"regions":[{"type":"commune","id":"1032041"},{"type":"country","id":"1022089"},{"type":"district","id":"1022173"},{"type":"province","id":"1029131"},{"type":"mountainarea","id":"8872348"},{"type":"protectedarea","id":"16522486"},{"type":"protectedarea","id":"9022883"},{"type":"protectedarea","id":"9015373"},{"type":"protectedarea","id":"9024021"},{"type":"protectedarea","id":"9023351"},{"type":"tourismarea","id":"1043712"}],"coordinates":[{"title":"DD","type":"dd","value":"51.732329, 11.025460"},{"title":"GMS","type":"dms","value":"51°43'56.4\"N 11°01'31.7\"E"},{"title":"UTM","type":"utm","value":"32U 639870 5733209"},{"title":"w3w","type":"w3w","value":"///neben.ausgeglichen.meisterwerke"}],"communityInfo":{"ratingDetails":{"oneStar":0,"twoStar":0,"threeStar":0,"fourStar":0,"fiveStar":0},"rating":0.0,"ratingCount":0,"commentCount":1},"geoJson":{"type":"LineString","coordinates":[{"x":639869.968786782,"z":5733209.163192096,"y":448.9},{"x":639872.4770225682,"z":5733203.4458951615,"y":448.8},{"x":639879.3494369838,"z":5733187.388771221,"y":448.5},{"x":639887.8420291584,"z":5733172.712095211,"y":448.4},{"x":639896.9589670107,"z":5733150.485229332,"y":448.6},{"x":639879.8997238302,"z":5733127.754029196,"y":448.9},{"x":639855.173131051,"z":5733092.457130134,"y":451.2},{"x":639833.00645133,"z":5733062.016780498,"y":452.3},{"x":639810.7704435465,"z":5733031.574617831,"y":452.5},{"x":639793.4816277972,"z":5733009.61638955,"y":453.3},{"x":639763.081262178,"z":5732991.968515383,"y":454.3},{"x":639736.3748900921,"z":5732980.655378829,"y":455.7},{"x":639704.58627406,"z":5732968.199863702,"y":457.5},{"x":639670.1981714303,"z":5732954.782188812,"y":459.4},{"x":639636.5571460455,"z":5732941.830612404,"y":461.1},{"x":639602.8499841914,"z":5732928.766148589,"y":463.4},{"x":639569.1395747487,"z":5732915.813115103,"y":466.1},{"x":639558.7759550022,"z":5732910.740669158,"y":467.0},{"x":639546.2680778531,"z":5732910.728050848,"y":467.1},{"x":639511.0579200231,"z":5732916.986516436,"y":466.1},{"x":639475.7788069514,"z":5732923.243314808,"y":465.0},{"x":639467.9542627546,"z":5732923.8057006905,"y":464.9},{"x":639462.3486529835,"z":5732924.095664465,"y":464.8},{"x":639453.0295716348,"z":5732923.726405051,"y":464.9},{"x":639417.8101999387,"z":5732912.847082038,"y":467.2},{"x":639382.5937623779,"z":5732901.856806236,"y":468.9},{"x":639362.9002058033,"z":5732894.3009135015,"y":469.6},{"x":639357.761504421,"z":5732887.70413005,"y":470.7},{"x":639349.4503195109,"z":5732865.884598226,"y":473.8},{"x":639344.7877084991,"z":5732852.067359315,"y":475.3},{"x":639339.2659570191,"z":5732834.331327578,"y":476.8},{"x":639335.8127212416,"z":5732816.763799532,"y":478.3},{"x":639330.9649475798,"z":5732792.146643363,"y":479.8},{"x":639324.1005434344,"z":5732770.478467859,"y":480.7},{"x":639321.4590814607,"z":5732751.041530643,"y":481.2},{"x":639316.9514219055,"z":5732734.112585379,"y":481.5},{"x":639304.957615088,"z":5732695.4983155755,"y":481.8},{"x":639299.7207201528,"z":5732682.444263057,"y":481.7},{"x":639286.197703372,"z":5732654.137433011,"y":481.1},{"x":639258.8129322559,"z":5732652.267568545,"y":479.7},{"x":639217.7733510651,"z":5732649.3528039055,"y":476.2},{"x":639180.0423185679,"z":5732646.752344609,"y":473.6},{"x":639176.7997222748,"z":5732646.5514835995,"y":473.3},{"x":639173.5687345997,"z":5732608.402230945,"y":474.0},{"x":639170.3376772071,"z":5732570.252983213,"y":474.8},{"x":639167.1065500973,"z":5732532.1037404,"y":474.9},{"x":639163.8753532709,"z":5732493.954502507,"y":474.5},{"x":639160.6421461764,"z":5732478.39637706,"y":474.2},{"x":639158.8869770132,"z":5732451.861712476,"y":473.6},{"x":639157.2161949842,"z":5732424.772948715,"y":472.8},{"x":639155.5453844763,"z":5732397.684186828,"y":472.0},{"x":639152.7820104833,"z":5732360.104325306,"y":470.8},{"x":639149.9495138638,"z":5732322.52256078,"y":469.7},{"x":639147.1860165156,"z":5732284.9427076485,"y":469.1},{"x":639144.9934384102,"z":5732241.703016917,"y":468.9},{"x":639142.8038664939,"z":5732198.352128723,"y":469.2},{"x":639147.9148629052,"z":5732168.445923925,"y":469.1},{"x":639153.0289780251,"z":5732138.42852288,"y":468.2},{"x":639161.1666732158,"z":5732104.043166969,"y":468.5},{"x":639169.2353981403,"z":5732069.6559165595,"y":471.0},{"x":639177.3702104398,"z":5732035.381787929,"y":473.9},{"x":639184.3969955726,"z":5732001.188352467,"y":476.2},{"x":639191.4898540908,"z":5731967.10803606,"y":478.5},{"x":639198.582792082,"z":5731933.027729609,"y":480.5},{"x":639186.0035410727,"z":5731928.006252016,"y":480.4},{"x":639178.3218586321,"z":5731923.342637649,"y":480.7},{"x":639153.4426277581,"z":5731908.18835759,"y":481.6},{"x":639120.9535995857,"z":5731888.261383462,"y":482.7},{"x":639094.942853271,"z":5731871.518163073,"y":483.0},{"x":639063.4141234652,"z":5731846.832775972,"y":482.9},{"x":639031.8850854099,"z":5731822.147592165,"y":482.2},{"x":639000.3557391067,"z":5731797.462611651,"y":481.2},{"x":638975.6732286903,"z":5731777.640668637,"y":480.2},{"x":638951.6871765663,"z":5731752.607608388,"y":479.3},{"x":638933.464479399,"z":5731731.628566849,"y":478.6},{"x":638915.310696954,"z":5731710.6514981855,"y":478.0},{"x":638902.5385200182,"z":5731700.061143476,"y":477.4},{"x":638892.5568956321,"z":5731693.5540272035,"y":476.9},{"x":638882.325134807,"z":5731688.598043984,"y":476.3},{"x":638870.5969247294,"z":5731685.27013907,"y":475.5},{"x":638843.9203537083,"z":5731680.083703651,"y":473.4},{"x":638817.3097408708,"z":5731675.010514474,"y":471.3},{"x":638790.3584909937,"z":5731672.26509303,"y":468.9},{"x":638763.4041563908,"z":5731669.631017835,"y":466.7},{"x":638725.8476068699,"z":5731657.913654423,"y":465.0},{"x":638688.3599639293,"z":5731646.198474641,"y":464.0},{"x":638650.8752167362,"z":5731634.372375081,"y":463.6},{"x":638604.1037289974,"z":5731618.396153532,"y":463.8},{"x":638557.4040890547,"z":5731602.311068473,"y":463.8},{"x":638538.0978496436,"z":5731600.556198781,"y":463.1},{"x":638507.7634738743,"z":5731600.167602252,"y":462.3},{"x":638482.3636941222,"z":5731598.801916604,"y":461.9},{"x":638470.0011892105,"z":5731595.902678255,"y":461.8},{"x":638454.7877560979,"z":5731588.58501108,"y":461.8},{"x":638434.7886526275,"z":5731571.787948074,"y":462.3},{"x":638414.7203440362,"z":5731554.989070134,"y":462.9},{"x":638386.5880780534,"z":5731532.29329316,"y":463.5},{"x":638357.3202401572,"z":5731503.11195139,"y":464.0},{"x":638327.3108851677,"z":5731465.675318424,"y":464.0},{"x":638302.6155552226,"z":5731431.055549859,"y":464.0},{"x":638295.3744883256,"z":5731417.836463983,"y":464.4},{"x":638277.3391947784,"z":5731384.84629453,"y":464.5},{"x":638261.1939442172,"z":5731356.025607018,"y":463.9},{"x":638245.05154975,"z":5731327.093773754,"y":462.8},{"x":638233.4281119483,"z":5731307.30004634,"y":461.6},{"x":638204.8203982282,"z":5731274.131529359,"y":457.8},{"x":638192.8877880701,"z":5731260.561410271,"y":455.5},{"x":638182.564153325,"z":5731248.815996194,"y":453.5},{"x":638172.7413116177,"z":5731231.408783468,"y":450.4},{"x":638159.9329515977,"z":5731199.341389603,"y":445.4},{"x":638147.0583865058,"z":5731167.16093757,"y":442.5},{"x":638134.1836439845,"z":5731134.980522625,"y":439.7},{"x":638126.4479755824,"z":5731124.641586473,"y":438.6},{"x":638118.3506490403,"z":5731117.408740259,"y":437.6},{"x":638107.1986520129,"z":5731110.648640851,"y":436.2},{"x":638088.7040566269,"z":5731101.906852678,"y":434.4},{"x":638069.7268319498,"z":5731090.592356903,"y":432.5},{"x":638045.3643338837,"z":5731071.4517798675,"y":428.6},{"x":638030.4432900926,"z":5731063.475792314,"y":426.8},{"x":638005.2295324603,"z":5731055.2180520585,"y":425.1},{"x":637980.0847754121,"z":5731046.962330216,"y":422.0},{"x":637943.792734259,"z":5731034.284131888,"y":415.6},{"x":637924.9777801388,"z":5731029.651748426,"y":413.8},{"x":637899.9926065421,"z":5731028.189187889,"y":412.9},{"x":637877.9382659859,"z":5731028.253619422,"y":410.6},{"x":637856.5017298255,"z":5731031.005881469,"y":407.7},{"x":637846.0130834649,"z":5731032.833465145,"y":406.9},{"x":637833.3048101782,"z":5731034.934232873,"y":406.1},{"x":637814.818275271,"z":5731035.986774507,"y":405.2},{"x":637798.7282198707,"z":5731037.883888182,"y":405.0},{"x":637790.9756922376,"z":5731030.661020652,"y":405.4},{"x":637778.457539746,"z":5731020.748356805,"y":407.1},{"x":637756.0225931096,"z":5730999.324944787,"y":411.8},{"x":637745.3975876657,"z":5730985.902990697,"y":413.3},{"x":637736.9352538802,"z":5730971.761159439,"y":414.2},{"x":637725.6468377019,"z":5730947.192645563,"y":415.7},{"x":637718.8726752497,"z":5730931.984125676,"y":416.8},{"x":637708.8934430175,"z":5730917.689624642,"y":418.0},{"x":637697.0686824974,"z":5730907.684841044,"y":419.0},{"x":637684.5674818027,"z":5730899.664737606,"y":419.9},{"x":637670.8554311446,"z":5730892.947015715,"y":420.7},{"x":637656.7645399793,"z":5730887.443119733,"y":421.2},{"x":637629.1505446522,"z":5730886.021434973,"y":420.7},{"x":637604.4675437039,"z":5730886.126607674,"y":419.8},{"x":637587.8707311896,"z":5730883.781760902,"y":419.8},{"x":637575.0231849453,"z":5730878.3120332165,"y":420.7},{"x":637562.1998876987,"z":5730871.952724195,"y":421.9},{"x":637551.1490923909,"z":5730863.9725437565,"y":423.5},{"x":637538.7052076582,"z":5730853.839973617,"y":425.3},{"x":637526.1177362606,"z":5730841.366543096,"y":427.0},{"x":637518.66579683,"z":5730830.702505123,"y":427.9},{"x":637491.926285575,"z":5730837.763067461,"y":427.7},{"x":637457.1279690183,"z":5730846.273290732,"y":427.7},{"x":637425.2251150386,"z":5730855.085249246,"y":428.0},{"x":637387.8886194091,"z":5730865.418583498,"y":428.2},{"x":637350.6213678947,"z":5730875.754073942,"y":428.7},{"x":637313.2851991167,"z":5730886.087955717,"y":429.4},{"x":637273.2611178468,"z":5730896.126343321,"y":430.8},{"x":637233.2372083016,"z":5730906.165046064,"y":432.2},{"x":637193.2134704823,"z":5730916.2040639445,"y":432.8},{"x":637153.2559587538,"z":5730926.356478367,"y":433.4},{"x":637136.2824884033,"z":5730930.234788068,"y":433.3},{"x":637129.9408344078,"z":5730952.4304017825,"y":432.8},{"x":637109.4799537092,"z":5730990.489466105,"y":432.3},{"x":637089.0223887295,"z":5731028.437408323,"y":431.8},{"x":637076.012774958,"z":5731054.346690135,"y":431.0},{"x":637063.0753880636,"z":5731080.146680514,"y":429.6},{"x":637041.4079034643,"z":5731119.397301452,"y":427.0},{"x":637020.3594050921,"z":5731158.776113363,"y":424.5},{"x":636999.314239278,"z":5731198.043807781,"y":422.4},{"x":636978.2663608296,"z":5731237.4227886945,"y":420.8},{"x":636967.8506339154,"z":5731239.142862112,"y":420.7},{"x":636932.1953361892,"z":5731258.984239246,"y":420.7},{"x":636896.4742694179,"z":5731278.712786282,"y":421.1},{"x":636860.822562123,"z":5731298.4434578065,"y":421.4},{"x":636830.0425742504,"z":5731316.971210321,"y":420.9},{"x":636829.901406592,"z":5731317.078662092,"y":420.9},{"x":636798.9114085499,"z":5731335.712177942,"y":420.1},{"x":636767.9907166242,"z":5731354.347755218,"y":418.9},{"x":636741.1941860402,"z":5731368.755324286,"y":417.1},{"x":636727.7959793434,"z":5731375.959161375,"y":415.6},{"x":636714.4668852224,"z":5731383.164907074,"y":414.2},{"x":636680.5166295059,"z":5731401.384969155,"y":408.4},{"x":636652.7445414423,"z":5731416.1003836375,"y":401.2},{"x":636644.6901279403,"z":5731414.880460994,"y":398.0},{"x":636640.588214474,"z":5731410.65175446,"y":395.6},{"x":636651.6620977493,"z":5731399.934877884,"y":398.2},{"x":636656.2642312646,"z":5731388.263564974,"y":398.1},{"x":636664.0051226389,"z":5731373.004992555,"y":398.5},{"x":636680.1144527658,"z":5731344.84185685,"y":399.8},{"x":636693.7547927108,"z":5731321.063162203,"y":400.6},{"x":636696.2209378253,"z":5731316.789972794,"y":400.7},{"x":636700.2887369283,"z":5731304.4364994895,"y":399.9},{"x":636700.0256648288,"z":5731293.746112749,"y":397.9},{"x":636697.4197868479,"z":5731285.329149865,"y":395.2},{"x":636683.1910057189,"z":5731251.780695624,"y":381.7},{"x":636674.9973735521,"z":5731230.1920183785,"y":372.6},{"x":636673.7855382233,"z":5731216.248680039,"y":369.0},{"x":636672.5553290258,"z":5731205.532075495,"y":366.1},{"x":636673.7907455692,"z":5731195.661312443,"y":364.9},{"x":636678.4037811079,"z":5731168.299289124,"y":363.0},{"x":636675.7931231942,"z":5731147.307142102,"y":359.2},{"x":636675.397026577,"z":5731144.069171299,"y":358.6},{"x":636671.4492116461,"z":5731129.050098498,"y":355.4},{"x":636662.3715688399,"z":5731114.559652219,"y":350.2},{"x":636654.4739560457,"z":5731102.438175004,"y":346.2},{"x":636649.6285448405,"z":5731082.275736829,"y":345.2},{"x":636646.641653324,"z":5731067.505307621,"y":345.8},{"x":636637.9569358276,"z":5731056.364079245,"y":343.8},{"x":636632.9895979129,"z":5731053.447341367,"y":342.2},{"x":636620.1596531175,"z":5731047.312843087,"y":338.1},{"x":636615.9192431086,"z":5731043.080419728,"y":337.5},{"x":636610.9912935834,"z":5731036.158557642,"y":337.4},{"x":636592.0023850566,"z":5731017.5047329655,"y":336.5},{"x":636565.6901395712,"z":5731008.89068025,"y":331.8},{"x":636522.053729289,"z":5731004.370180683,"y":323.3},{"x":636506.6640626385,"z":5731005.956512959,"y":319.6},{"x":636484.509870046,"z":5731019.934782477,"y":309.1},{"x":636462.3558016198,"z":5731033.913147552,"y":299.5},{"x":636437.8265609267,"z":5731041.150302226,"y":292.8},{"x":636430.5431148469,"z":5731044.625527697,"y":290.4},{"x":636437.2464022553,"z":5731049.81471794,"y":289.3},{"x":636442.4507280864,"z":5731059.30340387,"y":286.6},{"x":636463.3412176835,"z":5731076.672725874,"y":284.3},{"x":636477.2309978517,"z":5731089.623816126,"y":281.9},{"x":636493.8446534016,"z":5731104.095392064,"y":279.8},{"x":636507.8573754559,"z":5731117.606321269,"y":278.5},{"x":636514.5751630547,"z":5731127.358645391,"y":276.3},{"x":636524.0732852002,"z":5731146.756678774,"y":270.3},{"x":636526.4154748999,"z":5731152.161732953,"y":269.9},{"x":636522.5016148374,"z":5731158.8440316,"y":269.6},{"x":636525.2283366736,"z":5731162.812812512,"y":269.6},{"x":636527.9098746377,"z":5731168.449626527,"y":270.1},{"x":636527.8377862652,"z":5731168.5589576615,"y":270.1},{"x":636526.798033269,"z":5731176.32065336,"y":269.7},{"x":636523.3946325289,"z":5731184.574748357,"y":268.9},{"x":636517.3153455969,"z":5731192.0886699045,"y":268.3},{"x":636492.10714207,"z":5731211.659629689,"y":271.5},{"x":636466.8270478615,"z":5731231.340044745,"y":269.0},{"x":636456.5269129733,"z":5731213.478377632,"y":271.1},{"x":636456.1244999958,"z":5731213.022349148,"y":271.2},{"x":636436.3909701597,"z":5731193.792523945,"y":273.6},{"x":636416.2578779113,"z":5731173.995551709,"y":276.6},{"x":636379.317833726,"z":5731157.0824185535,"y":276.3},{"x":636361.907880784,"z":5731149.044127199,"y":275.4},{"x":636342.3114810187,"z":5731140.056490012,"y":274.3},{"x":636305.3739635765,"z":5731123.032705556,"y":279.4},{"x":636261.1136517894,"z":5731121.168358758,"y":278.1},{"x":636231.0139720587,"z":5731127.3656429555,"y":274.7},{"x":636213.2672167948,"z":5731126.663479446,"y":277.2},{"x":636184.3629067626,"z":5731139.792907591,"y":282.7},{"x":636164.9492301815,"z":5731159.855859761,"y":279.0},{"x":636145.5357054749,"z":5731179.918884662,"y":280.8},{"x":636119.1397044555,"z":5731215.373075309,"y":275.0},{"x":636106.2377204355,"z":5731245.182447293,"y":273.0},{"x":636092.960514212,"z":5731281.213580071,"y":275.3},{"x":636089.3148465733,"z":5731318.951464867,"y":273.4},{"x":636085.7382872192,"z":5731356.691218323,"y":269.1},{"x":636084.6693417861,"z":5731383.481631691,"y":268.6},{"x":636083.5343270034,"z":5731410.158978925,"y":270.0},{"x":636082.8947627519,"z":5731426.166506723,"y":271.5},{"x":636084.3664877656,"z":5731453.581936678,"y":269.8},{"x":636085.8411887502,"z":5731480.886166125,"y":270.2},{"x":636085.6852057574,"z":5731514.823367553,"y":273.0},{"x":636085.5292086415,"z":5731548.760570553,"y":273.9},{"x":636086.072837095,"z":5731564.466199137,"y":273.1},{"x":636084.4452309408,"z":5731578.66651878,"y":273.3},{"x":636080.1688800522,"z":5731583.447521067,"y":274.3},{"x":636074.9765898401,"z":5731586.311980269,"y":274.9},{"x":636068.5950762869,"z":5731587.1412379155,"y":275.7},{"x":636059.6849730731,"z":5731586.900690601,"y":277.0},{"x":636049.2913389435,"z":5731585.284712471,"y":278.7},{"x":636043.2130951752,"z":5731582.561123085,"y":280.2},{"x":636035.8074949681,"z":5731580.358130304,"y":281.8},{"x":636028.3027648083,"z":5731576.705790502,"y":283.4},{"x":635994.2293285764,"z":5731550.970101746,"y":289.6},{"x":635960.1555457406,"z":5731525.2346499935,"y":294.5},{"x":635935.3705569219,"z":5731513.882926292,"y":296.2},{"x":635910.5884588484,"z":5731502.420124181,"y":298.0},{"x":635876.0729974252,"z":5731487.912959782,"y":298.1},{"x":635839.4338144273,"z":5731467.562082204,"y":302.0},{"x":635803.6955961579,"z":5731452.243496783,"y":303.6},{"x":635770.5914386061,"z":5731444.340807355,"y":302.0},{"x":635728.6249365816,"z":5731436.978656059,"y":302.0},{"x":635706.7469034683,"z":5731435.72184606,"y":300.9},{"x":635674.9617756517,"z":5731437.870772478,"y":297.6},{"x":635628.7143437378,"z":5731448.310767806,"y":292.2},{"x":635582.5332008912,"z":5731458.864244773,"y":293.7},{"x":635538.6417841486,"z":5731479.383879005,"y":294.7},{"x":635502.2439757233,"z":5731504.000236368,"y":296.3},{"x":635484.9875894376,"z":5731523.678505852,"y":294.8},{"x":635474.4880173937,"z":5731541.424074357,"y":292.4},{"x":635457.6110798682,"z":5731567.567026462,"y":291.8},{"x":635448.825493647,"z":5731578.125331147,"y":294.0},{"x":635435.2727962446,"z":5731601.464338711,"y":294.3},{"x":635430.222731194,"z":5731609.340988574,"y":294.4},{"x":635424.4521005126,"z":5731618.311107989,"y":294.7},{"x":635419.7832728728,"z":5731624.862618671,"y":295.6},{"x":635415.7181578944,"z":5731632.09805051,"y":296.4},{"x":635411.2658762992,"z":5731640.881040588,"y":297.5},{"x":635408.7893854118,"z":5731648.159160792,"y":297.9},{"x":635406.7967393305,"z":5731658.009783711,"y":297.7},{"x":635405.7297707344,"z":5731695.14954019,"y":294.2},{"x":635410.7274784918,"z":5731722.659366308,"y":290.6},{"x":635417.7247674714,"z":5731747.7747100545,"y":287.4},{"x":635420.1355821674,"z":5731766.089858228,"y":285.8},{"x":635418.530799874,"z":5731779.511947373,"y":285.9},{"x":635413.1857961642,"z":5731803.516679107,"y":286.4},{"x":635412.9159461039,"z":5731828.993175273,"y":286.3},{"x":635410.3834416032,"z":5731843.503166231,"y":287.3},{"x":635403.0916685809,"z":5731860.222219674,"y":289.2},{"x":635392.7842153392,"z":5731870.850992995,"y":290.7},{"x":635383.4456537658,"z":5731873.716024017,"y":291.3},{"x":635372.5749699937,"z":5731871.866041197,"y":291.0},{"x":635362.5080812809,"z":5731863.249427674,"y":290.8},{"x":635354.5669216615,"z":5731852.686841339,"y":291.3},{"x":635343.7002709222,"z":5731837.816958296,"y":292.6},{"x":635320.8445575592,"z":5731813.833830957,"y":294.2},{"x":635304.9465385702,"z":5731790.705310862,"y":295.2},{"x":635292.7221264741,"z":5731774.908837199,"y":294.9},{"x":635289.030049497,"z":5731765.684547926,"y":295.3},{"x":635281.2587203903,"z":5731748.783543027,"y":295.4},{"x":635278.9505373462,"z":5731736.925629322,"y":296.6},{"x":635288.9000092122,"z":5731703.585364448,"y":306.9},{"x":635285.5634996315,"z":5731683.687497683,"y":310.8},{"x":635283.486787764,"z":5731673.505036396,"y":313.0},{"x":635280.0921947116,"z":5731666.069265927,"y":313.9},{"x":635267.7991785343,"z":5731637.362253567,"y":318.4},{"x":635255.4399265731,"z":5731608.542218566,"y":323.5},{"x":635243.9588625481,"z":5731588.203259302,"y":325.3},{"x":635237.2875546673,"z":5731579.232923355,"y":324.8},{"x":635229.3819025962,"z":5731569.8956304975,"y":323.5},{"x":635220.1106234684,"z":5731565.084294824,"y":319.6},{"x":635204.7785431577,"z":5731556.883191411,"y":314.3},{"x":635188.9659006902,"z":5731548.557964139,"y":310.6},{"x":635160.5485183124,"z":5731535.999859928,"y":305.5},{"x":635147.4150954271,"z":5731530.862527499,"y":303.4},{"x":635133.1457012891,"z":5731521.688605871,"y":303.2},{"x":635125.4087221369,"z":5731516.362178039,"y":303.6},{"x":635120.3933471116,"z":5731515.226175099,"y":303.4},{"x":635114.1356965587,"z":5731519.175864154,"y":301.9},{"x":635111.775855211,"z":5731522.117226377,"y":301.2},{"x":635106.4594055365,"z":5731532.212687209,"y":299.5},{"x":635099.4728376634,"z":5731540.1490191305,"y":299.4},{"x":635065.0344871286,"z":5731558.81169754,"y":303.8},{"x":635026.6891728372,"z":5731576.257103238,"y":306.1},{"x":634999.8324978335,"z":5731588.00126781,"y":309.2},{"x":634972.9759520682,"z":5731599.745573577,"y":312.6},{"x":634940.6683439423,"z":5731621.470749107,"y":313.8},{"x":634919.1531250555,"z":5731640.257841758,"y":313.1},{"x":634897.5689960431,"z":5731659.04317534,"y":312.0},{"x":634859.333601337,"z":5731690.5142946895,"y":310.4},{"x":634821.0266388034,"z":5731722.095052403,"y":311.0},{"x":634782.7426165509,"z":5731747.667460789,"y":315.3},{"x":634766.0900291489,"z":5731765.583673456,"y":316.3},{"x":634735.3191950194,"z":5731799.70349259,"y":319.7},{"x":634704.54579634,"z":5731833.9346969165,"y":324.9},{"x":634693.2251925562,"z":5731856.667500181,"y":325.7},{"x":634682.5200796659,"z":5731900.337800919,"y":324.6},{"x":634671.8121546047,"z":5731944.119326628,"y":326.0},{"x":634667.4800849771,"z":5731969.153302132,"y":327.2},{"x":634660.2214056362,"z":5731987.320869153,"y":329.3},{"x":634648.8962337908,"z":5731992.137223312,"y":331.7},{"x":634630.7894010709,"z":5731992.098571085,"y":333.9},{"x":634611.7750754165,"z":5731989.810102173,"y":335.5},{"x":634596.8110430199,"z":5731985.960655601,"y":336.5},{"x":634585.0893662194,"z":5731990.09886811,"y":336.6},{"x":634554.2739779901,"z":5731997.51083321,"y":336.3},{"x":634522.1338001806,"z":5732002.773260846,"y":335.1},{"x":634482.2762870266,"z":5732007.162240662,"y":335.3},{"x":634471.1695946058,"z":5732008.980204468,"y":335.5},{"x":634461.7687504531,"z":5732011.622682221,"y":335.6},{"x":634454.0618877929,"z":5732015.534475143,"y":335.7},{"x":634448.6193235792,"z":5732020.063100534,"y":335.6},{"x":634443.7233490209,"z":5732024.828877817,"y":335.6},{"x":634438.6396504012,"z":5732034.040925296,"y":335.5},{"x":634434.6736899926,"z":5732045.3971511,"y":335.5},{"x":634432.0080906827,"z":5732057.233197005,"y":335.7},{"x":634427.2450972879,"z":5732082.923523255,"y":335.9},{"x":634423.4791534683,"z":5732099.7379024625,"y":335.9},{"x":634417.7489683767,"z":5732115.053223132,"y":336.0},{"x":634411.6192697474,"z":5732129.801483354,"y":335.5},{"x":634403.1770703039,"z":5732143.15268716,"y":335.0},{"x":634383.9764550789,"z":5732166.009778836,"y":333.7},{"x":634375.7487549544,"z":5732173.913934972,"y":332.8},{"x":634365.4610805626,"z":5732181.318046012,"y":331.4},{"x":634358.3307653714,"z":5732184.355091341,"y":330.7},{"x":634345.1674800207,"z":5732185.562068902,"y":330.1},{"x":634333.1595909072,"z":5732184.908091781,"y":329.6},{"x":634321.6766338544,"z":5732182.710191502,"y":329.5},{"x":634312.0494504502,"z":5732180.895627821,"y":329.4},{"x":634303.1908350396,"z":5732178.76772209,"y":329.5},{"x":634287.8602212345,"z":5732173.128898138,"y":330.7},{"x":634271.7384403157,"z":5732163.46289849,"y":333.0},{"x":634250.5248798721,"z":5732147.763364248,"y":334.6},{"x":634233.3414513425,"z":5732133.84050617,"y":334.9},{"x":634215.6122882348,"z":5732122.240090106,"y":334.3},{"x":634204.3916616479,"z":5732115.375623434,"y":333.8},{"x":634182.2373676226,"z":5732106.439520039,"y":331.8},{"x":634173.4683641443,"z":5732103.535265229,"y":330.9},{"x":634161.3655910584,"z":5732098.650479123,"y":329.6},{"x":634144.6365697695,"z":5732088.412332441,"y":328.7},{"x":634134.9322086148,"z":5732081.699673768,"y":328.4},{"x":634124.7749632311,"z":5732076.421640959,"y":328.2},{"x":634113.7415817038,"z":5732072.900816415,"y":328.3},{"x":634099.6111649567,"z":5732066.292997218,"y":329.1},{"x":634090.7473030519,"z":5732059.157669113,"y":330.1},{"x":634077.525471049,"z":5732049.56949132,"y":331.3},{"x":634067.427274598,"z":5732042.0675207265,"y":332.3},{"x":634062.1655665442,"z":5732039.813187441,"y":332.6},{"x":634057.0567733945,"z":5732037.006520382,"y":332.9},{"x":634049.1015609265,"z":5732034.6805469645,"y":333.2},{"x":634037.7141255806,"z":5732047.063727155,"y":332.4},{"x":634028.77473575,"z":5732068.748403889,"y":331.4},{"x":634062.1040330979,"z":5732088.88669139,"y":328.2},{"x":634086.4193179546,"z":5732102.331017618,"y":327.5},{"x":634100.1214699708,"z":5732112.043290109,"y":327.7},{"x":634114.6325957956,"z":5732125.115579849,"y":327.0},{"x":634124.1306920405,"z":5732134.382188411,"y":325.7},{"x":634138.2628382547,"z":5732146.1090856735,"y":322.9},{"x":634150.2372422831,"z":5732153.216035225,"y":320.9},{"x":634164.8715092132,"z":5732159.058454371,"y":318.9},{"x":634177.9133946904,"z":5732162.410319543,"y":317.9},{"x":634204.1014557368,"z":5732183.3609828,"y":317.4},{"x":634230.2892991715,"z":5732204.311786303,"y":312.9},{"x":634237.3185918409,"z":5732212.845169329,"y":310.7},{"x":634239.720550203,"z":5732229.045004681,"y":306.1},{"x":634238.7210582226,"z":5732271.750551523,"y":297.2},{"x":634229.1327146,"z":5732260.700793597,"y":299.7},{"x":634219.1683052832,"z":5732255.9840947315,"y":300.9},{"x":634207.7752676116,"z":5732253.009871994,"y":302.0},{"x":634201.5775466381,"z":5732252.1771117635,"y":302.6},{"x":634195.4429618281,"z":5732251.568604013,"y":303.3},{"x":634182.6696323853,"z":5732251.117157011,"y":304.6},{"x":634164.816354692,"z":5732251.977141947,"y":306.4},{"x":634149.9514401519,"z":5732254.808536104,"y":306.3},{"x":634138.3116856884,"z":5732258.504800224,"y":305.8},{"x":634118.345173459,"z":5732268.656346045,"y":304.3},{"x":634106.2496774015,"z":5732273.898493508,"y":304.0},{"x":634069.4641202767,"z":5732287.608756749,"y":304.3},{"x":634032.6787719732,"z":5732301.319285442,"y":304.4},{"x":634006.771560049,"z":5732313.983991526,"y":302.0},{"x":633995.5168463434,"z":5732318.803630179,"y":301.1},{"x":633971.6547985843,"z":5732324.7347275745,"y":300.9},{"x":633944.1670408283,"z":5732326.674701549,"y":303.0},{"x":633913.4611787343,"z":5732330.087235869,"y":305.5},{"x":633882.821471147,"z":5732333.612994438,"y":305.9},{"x":633844.1642577562,"z":5732342.37874611,"y":304.4},{"x":633824.2702850562,"z":5732344.632369864,"y":305.2},{"x":633793.4501470604,"z":5732347.15234092,"y":309.6},{"x":633765.6834306215,"z":5732349.197153094,"y":310.0},{"x":633741.0173483298,"z":5732348.987509619,"y":311.3},{"x":633705.5360422968,"z":5732342.259236397,"y":316.4},{"x":633683.9793708662,"z":5732339.461636131,"y":317.2},{"x":633642.3793840618,"z":5732334.129416045,"y":319.9},{"x":633621.6159839772,"z":5732332.688498939,"y":324.5},{"x":633610.1373153721,"z":5732332.940514581,"y":326.3},{"x":633581.6033904498,"z":5732337.859304536,"y":322.3},{"x":633564.5852246277,"z":5732338.520973356,"y":321.3},{"x":633537.3167612895,"z":5732340.023842546,"y":318.3},{"x":633529.2763700823,"z":5732340.923570118,"y":317.4},{"x":633522.5569558863,"z":5732341.524472241,"y":316.5},{"x":633503.7092037708,"z":5732346.032698707,"y":315.9},{"x":633479.8770819274,"z":5732356.084281729,"y":314.7},{"x":633471.9113512443,"z":5732361.993721953,"y":312.9},{"x":633464.3819252035,"z":5732369.69522677,"y":310.6},{"x":633450.398632861,"z":5732386.239563922,"y":306.4},{"x":633434.8535824729,"z":5732401.741048039,"y":303.1},{"x":633422.4165451275,"z":5732412.094671073,"y":301.1},{"x":633409.8355528126,"z":5732422.6670730645,"y":299.7},{"x":633391.4066066571,"z":5732434.865176034,"y":299.8},{"x":633377.0050827353,"z":5732448.950447734,"y":300.6},{"x":633369.6111005854,"z":5732456.766949725,"y":301.2},{"x":633361.7543392146,"z":5732463.792246143,"y":301.9},{"x":633352.0271516907,"z":5732470.990611382,"y":302.7},{"x":633340.8968666806,"z":5732476.371367358,"y":303.6},{"x":633333.4796330006,"z":5732479.847348455,"y":304.2},{"x":633323.5072765604,"z":5732483.2557278825,"y":304.9},{"x":633304.3840243064,"z":5732487.757379692,"y":306.3},{"x":633284.2249461354,"z":5732492.23170129,"y":308.9},{"x":633252.4979064029,"z":5732502.965716953,"y":313.2},{"x":633244.756076309,"z":5732505.654273998,"y":313.9},{"x":633237.9928197652,"z":5732507.923597058,"y":313.9},{"x":633225.6902861487,"z":5732510.602860415,"y":314.1},{"x":633210.9105271786,"z":5732512.882814725,"y":314.9},{"x":633194.6497418811,"z":5732513.677009372,"y":316.5},{"x":633175.8852688862,"z":5732515.072762272,"y":317.7},{"x":633157.4616789261,"z":5732519.25961184,"y":314.9},{"x":633145.2179938687,"z":5732524.945203229,"y":312.7},{"x":633124.017517434,"z":5732534.845387244,"y":312.5},{"x":633086.8210636964,"z":5732556.452695607,"y":310.8},{"x":633064.0032503047,"z":5732572.65339756,"y":306.1},{"x":633019.2360667667,"z":5732590.500261135,"y":311.6},{"x":633011.8178342414,"z":5732596.647407429,"y":314.1},{"x":633009.6024331343,"z":5732607.271859228,"y":315.4},{"x":633006.8038356802,"z":5732621.664456449,"y":317.2},{"x":633002.5830428186,"z":5732637.577439016,"y":319.8},{"x":633002.590857064,"z":5732655.605104401,"y":320.6},{"x":633002.5544979199,"z":5732670.070624492,"y":321.5},{"x":632996.9618736873,"z":5732701.304120714,"y":327.4},{"x":632998.3725932739,"z":5732710.68893343,"y":327.9},{"x":633001.4832436881,"z":5732721.120149209,"y":327.7},{"x":633004.632044727,"z":5732730.1057266295,"y":327.3},{"x":633011.7405228359,"z":5732743.535791319,"y":325.1},{"x":633019.8421398444,"z":5732755.990564095,"y":322.1},{"x":633026.8050381513,"z":5732767.079916291,"y":320.4},{"x":633030.272503104,"z":5732771.845262668,"y":319.4},{"x":633039.0821794316,"z":5732783.651083555,"y":317.8},{"x":633070.6928124796,"z":5732813.86403999,"y":320.2},{"x":633085.1690432146,"z":5732823.037610354,"y":321.0},{"x":633093.2864866355,"z":5732832.26579281,"y":323.6},{"x":633108.1460833976,"z":5732840.002911654,"y":323.8},{"x":633122.5634059747,"z":5732846.170458779,"y":324.8},{"x":633149.8185913963,"z":5732852.899896578,"y":325.4},{"x":633174.0868733283,"z":5732854.988012577,"y":324.7},{"x":633206.5371946488,"z":5732853.397752385,"y":322.6},{"x":633236.8439742089,"z":5732851.862289992,"y":320.8},{"x":633253.5460140929,"z":5732847.407679226,"y":318.7},{"x":633291.3224913662,"z":5732840.394796769,"y":316.5},{"x":633307.5265418863,"z":5732836.483590129,"y":315.9},{"x":633317.6831904708,"z":5732836.529793561,"y":316.1},{"x":633329.7130948203,"z":5732836.2917506965,"y":315.8},{"x":633352.1742730143,"z":5732838.778021535,"y":316.1},{"x":633371.0109643679,"z":5732839.833066709,"y":315.5},{"x":633385.970528567,"z":5732838.559907684,"y":315.0},{"x":633401.4003668006,"z":5732835.184905885,"y":314.9},{"x":633425.7825446009,"z":5732825.1476151645,"y":312.7},{"x":633450.1648230677,"z":5732815.11044097,"y":309.6},{"x":633472.5354557135,"z":5732810.584139074,"y":307.9},{"x":633482.6172232381,"z":5732810.851250706,"y":308.0},{"x":633490.0366638282,"z":5732812.494492504,"y":308.4},{"x":633501.9605658904,"z":5732816.26016899,"y":309.0},{"x":633513.2010850003,"z":5732822.3446672885,"y":310.1},{"x":633530.2020242435,"z":5732832.699271574,"y":311.5},{"x":633553.8327600027,"z":5732851.019369412,"y":312.5},{"x":633561.6205118787,"z":5732857.012450097,"y":312.3},{"x":633591.3401588711,"z":5732882.838725657,"y":310.8},{"x":633601.5984464874,"z":5732894.684009813,"y":310.6},{"x":633620.6247062092,"z":5732922.452524745,"y":310.9},{"x":633633.818529379,"z":5732946.0602773875,"y":311.0},{"x":633639.7110579165,"z":5732963.576468757,"y":310.9},{"x":633640.5444743299,"z":5732973.836455188,"y":310.8},{"x":633640.2359219432,"z":5732988.072273571,"y":310.9},{"x":633639.1164612473,"z":5733001.618892542,"y":310.9},{"x":633636.1733941863,"z":5733018.789417657,"y":311.1},{"x":633628.278840075,"z":5733040.2798479805,"y":311.7},{"x":633621.8797095078,"z":5733049.680295798,"y":312.4},{"x":633617.1188909189,"z":5733057.232424109,"y":313.0},{"x":633611.5501352685,"z":5733063.984158316,"y":313.9},{"x":633581.0714028535,"z":5733092.887946498,"y":319.3},{"x":633568.4137638832,"z":5733103.791718475,"y":321.0},{"x":633559.5231569575,"z":5733113.348739454,"y":319.4},{"x":633549.5619365544,"z":5733118.982548432,"y":320.0},{"x":633536.6788015041,"z":5733122.758419149,"y":320.6},{"x":633525.8511620117,"z":5733124.585744568,"y":322.0},{"x":633512.2485264888,"z":5733124.225200819,"y":324.2},{"x":633498.3124341369,"z":5733123.410732085,"y":326.2},{"x":633488.9011531603,"z":5733123.940297765,"y":326.9},{"x":633479.9012216973,"z":5733124.592061857,"y":327.5},{"x":633468.0993710548,"z":5733129.287005725,"y":327.0},{"x":633455.1911056631,"z":5733136.623411338,"y":326.0},{"x":633429.9941375632,"z":5733159.2136871815,"y":322.6},{"x":633396.5905093981,"z":5733189.042580744,"y":320.2},{"x":633363.1872733837,"z":5733218.871690536,"y":319.6},{"x":633336.1429089401,"z":5733243.416551592,"y":319.3},{"x":633309.1017485084,"z":5733267.850351209,"y":318.5},{"x":633297.7438927452,"z":5733276.674821511,"y":318.4},{"x":633286.1834526078,"z":5733282.711930213,"y":318.9},{"x":633272.1197098906,"z":5733289.350517665,"y":319.3},{"x":633258.0134357561,"z":5733294.98648883,"y":319.6},{"x":633237.0774803184,"z":5733300.219279871,"y":319.9},{"x":633215.8830320277,"z":5733304.777634027,"y":318.3},{"x":633201.6491282744,"z":5733307.405797949,"y":316.3},{"x":633174.1128269607,"z":5733308.792040416,"y":313.4},{"x":633151.7712190574,"z":5733307.088601485,"y":312.5},{"x":633133.0405840359,"z":5733304.701734165,"y":312.2},{"x":633121.5950707445,"z":5733301.172093388,"y":312.2},{"x":633113.8295748603,"z":5733296.960761977,"y":312.3},{"x":633085.7188390177,"z":5733275.631021721,"y":313.1},{"x":633049.8025714653,"z":5733248.976356657,"y":315.9},{"x":633013.9549730802,"z":5733222.32377806,"y":317.8},{"x":632992.9466161244,"z":5733206.746178281,"y":317.2},{"x":632972.007177733,"z":5733191.170491234,"y":316.0},{"x":632951.035022702,"z":5733166.357738278,"y":316.5},{"x":632924.866228745,"z":5733136.845446548,"y":316.4},{"x":632901.372637868,"z":5733113.301755746,"y":315.1},{"x":632875.1238338915,"z":5733081.562026541,"y":316.5},{"x":632848.8056419013,"z":5733049.820619894,"y":321.4},{"x":632838.6443676595,"z":5733036.8666782,"y":323.5},{"x":632815.9056048241,"z":5732997.764060151,"y":332.3},{"x":632809.938945903,"z":5732990.818643424,"y":333.2},{"x":632798.6947812687,"z":5732979.616732003,"y":333.6},{"x":632779.9073834913,"z":5732960.982791994,"y":333.6},{"x":632756.303101259,"z":5732931.093945467,"y":335.5},{"x":632736.2870811515,"z":5732911.87140498,"y":334.9},{"x":632723.3907811937,"z":5732895.173407408,"y":339.6},{"x":632719.1589565566,"z":5732887.9399741385,"y":342.6},{"x":632712.9873830831,"z":5732875.647827768,"y":347.8},{"x":632709.563646758,"z":5732869.214654557,"y":350.2},{"x":632697.1082564491,"z":5732856.757002387,"y":351.6},{"x":632690.0042017327,"z":5732851.005868388,"y":351.5},{"x":632679.7881449639,"z":5732842.724617287,"y":351.5},{"x":632675.3846564837,"z":5732839.381516882,"y":351.5},{"x":632667.244761901,"z":5732833.603137914,"y":351.6},{"x":632648.8025632662,"z":5732825.439174615,"y":349.3},{"x":632636.9132662257,"z":5732820.341088205,"y":348.0},{"x":632607.7062912303,"z":5732814.230764774,"y":342.6},{"x":632578.4301991859,"z":5732808.118794614,"y":339.2},{"x":632539.2864593097,"z":5732798.85410178,"y":338.8},{"x":632506.7413103313,"z":5732793.5467946585,"y":338.9},{"x":632470.0166927878,"z":5732792.135887128,"y":336.9},{"x":632428.3618766366,"z":5732794.26789278,"y":334.5},{"x":632403.2963137182,"z":5732798.839240916,"y":333.6},{"x":632377.3524906887,"z":5732805.279395276,"y":332.2},{"x":632351.411660431,"z":5732811.608478901,"y":331.0},{"x":632322.817684283,"z":5732818.980806551,"y":333.6},{"x":632298.0440259674,"z":5732828.234094949,"y":334.7},{"x":632271.9662026376,"z":5732839.790138831,"y":336.2},{"x":632245.957555031,"z":5732851.348128573,"y":343.2},{"x":632231.0002216531,"z":5732870.985901068,"y":341.1},{"x":632220.7472810737,"z":5732890.413342221,"y":337.5},{"x":632215.9086287477,"z":5732911.540815566,"y":332.9},{"x":632212.6854482244,"z":5732929.03845214,"y":331.6},{"x":632214.3988121105,"z":5732963.802757184,"y":332.1},{"x":632218.6223694688,"z":5732987.171114387,"y":332.3},{"x":632224.4301142872,"z":5733013.363057346,"y":332.1},{"x":632230.2407086741,"z":5733039.443805593,"y":331.6},{"x":632240.1776961067,"z":5733063.629845485,"y":329.4},{"x":632250.0455319755,"z":5733087.8140945695,"y":327.5},{"x":632253.5978519645,"z":5733105.155755354,"y":327.0},{"x":632257.462247621,"z":5733126.400413959,"y":326.4},{"x":632272.2805413163,"z":5733167.295419986,"y":324.7},{"x":632279.3226818615,"z":5733199.083870727,"y":325.1},{"x":632286.0330442678,"z":5733232.977944814,"y":326.5},{"x":632293.1517401048,"z":5733267.105318,"y":328.9},{"x":632300.2012778997,"z":5733301.2308909325,"y":331.7},{"x":632305.5059795042,"z":5733338.649051751,"y":335.8},{"x":632310.0712473141,"z":5733354.236900706,"y":336.9},{"x":632326.8287813738,"z":5733384.388897951,"y":335.8},{"x":632343.6522278986,"z":5733414.653972944,"y":334.3},{"x":632365.3454588938,"z":5733446.271167728,"y":331.9},{"x":632387.0413311203,"z":5733477.777258348,"y":330.8},{"x":632404.097514305,"z":5733507.047163806,"y":332.1},{"x":632413.4660823287,"z":5733523.874201907,"y":332.6},{"x":632420.1542788829,"z":5733545.415840865,"y":334.5},{"x":632423.3833079897,"z":5733569.75982967,"y":338.0},{"x":632426.1598332818,"z":5733582.407498687,"y":339.7},{"x":632428.5688711636,"z":5733593.265023614,"y":341.3},{"x":632434.219951286,"z":5733604.319076491,"y":342.0},{"x":632438.9289479072,"z":5733611.787395881,"y":342.2},{"x":632445.9250850258,"z":5733618.98202315,"y":341.6},{"x":632467.8664864693,"z":5733638.476707741,"y":340.6},{"x":632481.8404282128,"z":5733648.303085236,"y":339.2},{"x":632511.0525488096,"z":5733664.539534916,"y":336.3},{"x":632540.2644849851,"z":5733680.776157399,"y":336.8},{"x":632569.4071958918,"z":5733697.011135403,"y":337.5},{"x":632600.3767095082,"z":5733725.201393668,"y":341.2},{"x":632618.3679010241,"z":5733737.248269913,"y":341.3},{"x":632647.9138187096,"z":5733751.268735119,"y":337.8},{"x":632677.5315463298,"z":5733765.179991978,"y":333.4},{"x":632690.852426179,"z":5733773.543131884,"y":331.4},{"x":632704.0459832078,"z":5733789.358751243,"y":330.0},{"x":632711.2753401772,"z":5733800.788582038,"y":329.4},{"x":632719.1977284276,"z":5733830.486702277,"y":329.5},{"x":632724.4050193612,"z":5733853.1026091445,"y":329.1},{"x":632726.1013872043,"z":5733872.621418631,"y":328.7},{"x":632722.9764486682,"z":5733886.337856858,"y":328.7},{"x":632714.4330246365,"z":5733903.806324495,"y":328.4},{"x":632705.6880514658,"z":5733915.816745131,"y":327.8},{"x":632695.3519590378,"z":5733922.666348726,"y":328.0},{"x":632683.182078173,"z":5733920.45393285,"y":330.2},{"x":632658.3268012267,"z":5733917.23969711,"y":335.8},{"x":632611.064366455,"z":5733922.783072984,"y":341.7},{"x":632573.3882889564,"z":5733931.583807535,"y":343.1},{"x":632538.4375329474,"z":5733944.462637126,"y":345.1},{"x":632503.4179262085,"z":5733957.339890107,"y":348.6},{"x":632492.9745675547,"z":5733960.403538106,"y":349.9},{"x":632480.2278388361,"z":5733961.737407663,"y":351.8},{"x":632476.6349792865,"z":5733961.75417423,"y":352.2},{"x":632462.323804721,"z":5733962.156692275,"y":353.9},{"x":632454.6004140403,"z":5733961.619710193,"y":354.5},{"x":632442.4488069315,"z":5733977.101930956,"y":354.1},{"x":632432.8737676024,"z":5733981.301339607,"y":353.9}]},"bbox":[[10.914537,51.711538],[11.025827,51.741074]],"pois":[{"id":"1623820","relations":["isElevationProfile"]},{"id":"17171278","relations":["isElevationProfile"]},{"id":"1685261","relations":["isElevationProfile"]},{"id":"51424182","relations":["isElevationProfile"]},{"id":"51424172","relations":["isElevationProfile"]},{"id":"51424171","relations":["isElevationProfile"]},{"id":"25849209","relations":["isElevationProfile"]},{"id":"51424175","relations":["isElevationProfile"]},{"id":"50773558","relations":["isElevationProfile"]},{"id":"1655238","relations":["isElevationProfile"]},{"id":"13221839","relations":["isElevationProfile","isRestStop"]},{"id":"1685259","relations":["isElevationProfile"]},{"id":"51424165","relations":["isElevationProfile"]},{"id":"1640116","relations":["isRecommendation","isElevationProfile"]}],"literature":[{"id":"12034554"},{"id":"13644952"},{"id":"19633528"},{"id":"12034516"},{"id":"19633526"},{"id":"12034512"}],"maps":[{"id":"19633034"},{"id":"19633695"},{"id":"19633866"},{"id":"19633296"},{"id":"19633096"},{"id":"19633112"}],"season":{"jan":"no","feb":"no","mar":"no","apr":"yes","may":"yes","jun":"yes","jul":"yes","aug":"yes","sep":"yes","oct":"yes","nov":"no","dec":"no"},"properties":[{"id":"57015209","name":"pointToPoint","title":"Von A nach B"},{"id":"1471946","name":"scenic","title":"aussichtsreich"},{"id":"1471941","name":"dining","title":"Einkehrmöglichkeit","iconUrl":"https://res.oastatic.com/v3/tags/svg/dining.svg"},{"id":"1471943","name":"suitableforfamilies","title":"familienfreundlich","iconUrl":"https://res.oastatic.com/v3/tags/svg/suitableforfamilies.svg"},{"id":"1471952","name":"geology","title":"geologische Highlights"},{"id":"54120147","name":"dogFriendly","title":"hundefreundlich"}],"metrics":{"duration":{"minimal":270.0},"elevation":{"elevationProfile":{"url":"https://www.outdooractive.com/api/v2/project/oad-harz/tour/6328796/export/elpro?key=IKLXEIKF-EMWGMGHI-4OSSNPLY","fallbackUrl":"https://www.outdooractive.com/api/v2/project/oad-harz/tour/6328796/export/elpro?type=png&key=IKLXEIKF-EMWGMGHI-4OSSNPLY"},"ascent":160,"descent":255,"minAltitude":268,"maxAltitude":483},"length":15616},"ratingInfo":{"stamina":3,"difficulty":2,"landscape":4,"experience":4},"wayTypeInfo":{"legend":[{"type":"asphalt","title":"Asphalt","length":1092.3998,"color":"#7b7b7b"},{"type":"gravel","title":"Schotterweg","length":9901.60576,"color":"#5a88ca"},{"type":"way","title":"Naturweg","length":4006.66388,"color":"#6dbf56"},{"type":"path","title":"Pfad","length":513.51593,"color":"#ff6060"},{"type":"street","title":"Straße","length":101.48598,"color":"#3f3f3f"}],"elements":[{"from":0.0,"to":0.0041394065,"type":"gravel","title":"Schotterweg"},{"from":0.0041394065,"to":0.0135374457,"type":"way","title":"Naturweg"},{"from":0.0135374457,"to":0.021615634,"type":"way","title":"Naturweg"},{"from":0.021615634,"to":0.0239776441,"type":"way","title":"Naturweg"},{"from":0.0239776441,"to":0.0445550687,"type":"way","title":"Naturweg"},{"from":0.0445550687,"to":0.0498515899,"type":"way","title":"Naturweg"},{"from":0.0498515899,"to":0.0607823863,"type":"way","title":"Naturweg"},{"from":0.0607823863,"to":0.0677994223,"type":"gravel","title":"Schotterweg"},{"from":0.0677994223,"to":0.0775988403,"type":"way","title":"Naturweg"},{"from":0.0775988403,"to":0.0786156521,"type":"way","title":"Naturweg"},{"from":0.0786156521,"to":0.0803172771,"type":"way","title":"Naturweg"},{"from":0.0803172771,"to":0.0965724715,"type":"way","title":"Naturweg"},{"from":0.0965724715,"to":0.1139262626,"type":"way","title":"Naturweg"},{"from":0.1139262626,"to":0.1293371435,"type":"gravel","title":"Schotterweg"},{"from":0.1293371435,"to":0.1335812618,"type":"gravel","title":"Schotterweg"},{"from":0.1335812618,"to":0.1549508959,"type":"gravel","title":"Schotterweg"},{"from":0.1549508959,"to":0.1668959214,"type":"gravel","title":"Schotterweg"},{"from":0.1668959214,"to":0.1736349682,"type":"gravel","title":"Schotterweg"},{"from":0.1736349682,"to":0.1793497798,"type":"gravel","title":"Schotterweg"},{"from":0.1793497798,"to":0.1830353734,"type":"gravel","title":"Schotterweg"},{"from":0.1830353734,"to":0.1896750684,"type":"gravel","title":"Schotterweg"},{"from":0.1896750684,"to":0.215562475,"type":"gravel","title":"Schotterweg"},{"from":0.215562475,"to":0.2273850434,"type":"gravel","title":"Schotterweg"},{"from":0.2273850434,"to":0.2511136074,"type":"gravel","title":"Schotterweg"},{"from":0.2511136074,"to":0.2763994831,"type":"gravel","title":"Schotterweg"},{"from":0.2763994831,"to":0.2985363033,"type":"gravel","title":"Schotterweg"},{"from":0.2985363033,"to":0.3139756842,"type":"way","title":"Naturweg"},{"from":0.3139756842,"to":0.3242265208,"type":"path","title":"Pfad"},{"from":0.3242265208,"to":0.3501345985,"type":"way","title":"Naturweg"},{"from":0.3501345985,"to":0.3727684148,"type":"path","title":"Pfad"},{"from":0.3727684148,"to":0.3792673976,"type":"street","title":"Straße"},{"from":0.3792673976,"to":0.4157623164,"type":"way","title":"Naturweg"},{"from":0.4157623164,"to":0.4191865845,"type":"gravel","title":"Schotterweg"},{"from":0.4191865845,"to":0.4237182509,"type":"gravel","title":"Schotterweg"},{"from":0.4237182509,"to":0.4299817352,"type":"gravel","title":"Schotterweg"},{"from":0.4299817352,"to":0.5059492128,"type":"way","title":"Naturweg"},{"from":0.5059492128,"to":0.5285555813,"type":"gravel","title":"Schotterweg"},{"from":0.5285555813,"to":0.5516528251,"type":"gravel","title":"Schotterweg"},{"from":0.5516528251,"to":0.5545988542,"type":"gravel","title":"Schotterweg"},{"from":0.5545988542,"to":0.5754851594,"type":"gravel","title":"Schotterweg"},{"from":0.5754851594,"to":0.5764738762,"type":"asphalt","title":"Asphalt"},{"from":0.5764738762,"to":0.5792974114,"type":"gravel","title":"Schotterweg"},{"from":0.5792974114,"to":0.6237408437,"type":"gravel","title":"Schotterweg"},{"from":0.6237408437,"to":0.6401198257,"type":"asphalt","title":"Asphalt"},{"from":0.6401198257,"to":0.6439012386,"type":"asphalt","title":"Asphalt"},{"from":0.6439012386,"to":0.6466964663,"type":"gravel","title":"Schotterweg"},{"from":0.6466964663,"to":0.673815622,"type":"gravel","title":"Schotterweg"},{"from":0.673815622,"to":0.7003644775,"type":"gravel","title":"Schotterweg"},{"from":0.7003644775,"to":0.7281030064,"type":"gravel","title":"Schotterweg"},{"from":0.7281030064,"to":0.7454038886,"type":"gravel","title":"Schotterweg"},{"from":0.7454038886,"to":0.7739023572,"type":"gravel","title":"Schotterweg"},{"from":0.7739023572,"to":0.8247621031,"type":"gravel","title":"Schotterweg"},{"from":0.8247621031,"to":0.8384786093,"type":"gravel","title":"Schotterweg"},{"from":0.8384786093,"to":0.9054971115,"type":"gravel","title":"Schotterweg"},{"from":0.9054971115,"to":0.9492652974,"type":"gravel","title":"Schotterweg"},{"from":0.9492652974,"to":0.9704422229,"type":"asphalt","title":"Asphalt"},{"from":0.9704422229,"to":0.9755988936,"type":"asphalt","title":"Asphalt"},{"from":0.9755988936,"to":0.9822263411,"type":"asphalt","title":"Asphalt"},{"from":0.9822263411,"to":0.9975761262,"type":"asphalt","title":"Asphalt"},{"from":0.9975761262,"to":0.9980715388,"type":"asphalt","title":"Asphalt"},{"from":0.9980715388,"to":1.0,"type":"gravel","title":"Schotterweg"}]},"teaserText":"Hexentanzplatz – Treseburg – Altenbrak – Wendefurth (ca. 16 km)","isWinter":false,"openState":"unknown","isClosedByClosure":false,"isIgnoreClosedByClosure":false}]}}